Workbook

Sheet query (18)
A1: ID | B1: Titre | C1: Date de l'Analyse | D1: Famille d'achat | E1: Segment | F1: Acheteur | G1: Sous famille | H1: Difficulté d’homologation venant des clients | I1: Diversité des outillages requis | J1: Dossier technique incomplet | K1: Qualité demandée inhabituelle sur le marché | L1: Services techniques peu ouverts aux produits de substitution | M1: Connaissance tardive des besoins | N1: Fournisseur imposé | O1: Limites géographiques imposées en interne | P1: Lourdeurs Administratives | Q1: Manque de communication interne | R1: Dépendance fournisseur | S1: Non-conformité réglementaire | T1: Problèmes de qualité | U1: Rupture d’approvisionnement | V1: Manque de transparence fournisseur | W1: Risque de dépendance technologique | X1: Insatisfaction des clients internes | Y1: Variabilité des coûts | Z1: Renforcement de la chaîne d’approvisionnement | AA1: Optimisation des coûts | AB1: Innovation fournisseur | AC1: Réduction des délais de livraison | AD1: Meilleure maîtrise des risque | AE1: Amélioration des relations fournisseurs | AF1: Automatisation et digitalisation | AG1: Amélioration de l’image RSE | AH1: Couverture contractuelle | AI1: Plan d'action | AJ1: Programmation | AK1: Levier Achat | AL1: Total_Opportun | AM1: Total_Risques | AN1: Total_CIT | AO1: Total_CIC | AP1: Total_CET | AQ1: Total_CEC | AR1: Type d'élément | AS1: Chemin d'accès | AT1: Montant commandé (K€)
A2: 6 | B2: Informatique & Telecom - Systèmes d'impression | C2: 46105 | D2: Systèmes d'impression | E2: Informatique & Telecom | F2: Julie GAUJARD | H2: 2 l’achat n’est remis en question que pour quelques pièces, | I2: 3 entraîne une réduction du nombre de fournisseurs potentiels, | J2: 3 reporte l’achat à cause d’une refonte nécessaire du dossier technique, | K2: 1 la forte concurrence amène les fournisseurs à s’adapter, | L2: 0 aucune difficulté pour recourir à des produits de substitution, | M2: 5 les achats ne sont que des achats d’urgence par manque de prévisions. | N2: 1 les impositions correspondent au meilleur choix, | O2: 0 il n’y a pas de limite géographique à l’achat, | P2: 4 le changement de fournisseur est long et fastidieux du fait des procédures administratives, | Q2: 5 le défaut de communication interne est à l’origine d’achats réalisés dans des conditions défavorables. | R2: 0 - Nul | S2: 0 - Nul | T2: 1 - Faible | U2: 3 - Important | V2: 1 - Faible | W2: 0 - Nul | X2: 3 - Important | Y2: 1 - Faible | Z2: 1 - Faible | AA2: 2 - Modéré | AC2: 1 - Faible | AD2: 1 - Faible | AE2: 1 - Faible | AF2: 1 - Faible | AG2: 3 - Important | AH2: 0 - Sécurisé | AJ2: T4 2028 | AL2: 0 | AM2: 0 | AN2: 7.2 | AO2: 12 | AP2: 0 | AQ2: 0 | AR2: Élément | AS2: sites/DNA948/Lists/Analyse de Portefeuille FINA | AT2: =IFERROR(ROUND(IF(Tableau_query__18[[#This Row],[Sous famille]]<>"",VLOOKUP(Tableau_query__18[[#This Row],[Sous famille]],'A013 TCD'!G:H,2,FALSE),VLOOKUP(Tableau_query__18[[#This Row],[Famille d''achat]],'A013 TCD'!D:E,2,FALSE))/1000,0),"") -> 1827
A3: 7 | B3: Informatique & Telecom - Services de Téléphonie | C3: 45916 | D3: Services de Téléphonie | E3: Informatique & Telecom | F3: Julie GAUJARD | H3: 1 les modifications sont minimes et sans conséquence sur l’achat, | I3: 0 égale à la moyenne du secteur, | J3: 2 retarde l’achat en l’absence de responsabilité technique, | K3: 0 la qualité demandée correspond à la moyenne du marché, | L3: 0 aucune difficulté pour recourir à des produits de substitution, | M3: 5 les achats ne sont que des achats d’urgence par manque de prévisions. | N3: 1 les impositions correspondent au meilleur choix, | O3: 0 il n’y a pas de limite géographique à l’achat, | P3: 4 le changement de fournisseur est long et fastidieux du fait des procédures administratives, | Q3: 5 le défaut de communication interne est à l’origine d’achats réalisés dans des conditions défavorables. | R3: 0 - Nul | S3: 0 - Nul | T3: 1 - Faible | U3: 1 - Faible | V3: 1 - Faible | W3: 0 - Nul | X3: 2 - Modéré | Y3: 2 - Modéré | Z3: 1 - Faible | AA3: 2 - Modéré | AB3: 0 - Nul | AC3: 1 - Faible | AD3: 1 - Faible | AE3: 2 - Modéré | AF3: 1 - Faible | AG3: 3 - Important | AH3: 0 - Sécurisé | AI3: Etudier le recours à une central d'achat car achats simples | AJ3: T2 2027 | AL3: 5.5 | AM3: 3.5 | AN3: 2.4 | AO3: 0 | AP3: 0 | AQ3: 0 | AR3: Élément | AS3: sites/DNA948/Lists/Analyse de Portefeuille FINA | AT3: =IFERROR(ROUND(IF(Tableau_query__18[[#This Row],[Sous famille]]<>"",VLOOKUP(Tableau_query__18[[#This Row],[Sous famille]],'A013 TCD'!G:H,2,FALSE),VLOOKUP(Tableau_query__18[[#This Row],[Famille d''achat]],'A013 TCD'!D:E,2,FALSE))/1000,0),"") -> 453
A4: 8 | B4: Informatique & Telecom - Services de réseaux informatiques | C4: 45918 | D4: Services de réseaux informatiques | E4: Informatique & Telecom | F4: Julie GAUJARD | H4: 1 les modifications sont minimes et sans conséquence sur l’achat, | I4: 1 de nombreux fournisseurs possèdent le parc requis, | J4: 5 les manques bloquent l’acte d’achat. | K4: 1 la forte concurrence amène les fournisseurs à s’adapter, | L4: 0 aucune difficulté pour recourir à des produits de substitution, | M4: 5 les achats ne sont que des achats d’urgence par manque de prévisions. | N4: 3 quelques rares fournisseurs imposés peuvent faire l’objet d’une mise en concurrence, | O4: 0 il n’y a pas de limite géographique à l’achat, | P4: 4 le changement de fournisseur est long et fastidieux du fait des procédures administratives, | Q4: 5 le défaut de communication interne est à l’origine d’achats réalisés dans des conditions défavorables. | R4: 1 - Faible | S4: 0 - Nul | T4: 1 - Faible | U4: 1 - Faible | V4: 2 - Modéré | W4: 1 - Faible | X4: 2 - Modéré | Y4: 1 - Faible | Z4: 0 - Nul | AA4: 2 - Modéré | AB4: 0 - Nul | AC4: 2 - Modéré | AD4: 1 - Faible | AE4: 2 - Modéré | AF4: 1 - Faible | AG4: 0 - Nul | AH4: 0 - Sécurisé | AI4: Conserver le fonctionnement d'un marché UGAP | AJ4: 2028 | AK4: Faire ou faire faire (externalisation) | AL4: 4 | AM4: 4.5 | AN4: 6.4 | AO4: 13.6 | AP4: 5.6 | AQ4: 0.8 | AR4: Élément | AS4: sites/DNA948/Lists/Analyse de Portefeuille FINA | AT4: =IFERROR(ROUND(IF(Tableau_query__18[[#This Row],[Sous famille]]<>"",VLOOKUP(Tableau_query__18[[#This Row],[Sous famille]],'A013 TCD'!G:H,2,FALSE),VLOOKUP(Tableau_query__18[[#This Row],[Famille d''achat]],'A013 TCD'!D:E,2,FALSE))/1000,0),"") -> 1352
A5: 9 | B5: Informatique & Telecom - Réseau informatique | C5: 45918 | D5: Réseau informatique | E5: Informatique & Telecom | F5: Laurine AUVRAY | H5: 2 l’achat n’est remis en question que pour quelques pièces, | I5: 1 de nombreux fournisseurs possèdent le parc requis, | J5: 5 les manques bloquent l’acte d’achat. | K5: 1 la forte concurrence amène les fournisseurs à s’adapter, | L5: 3 oblige à n’acheter que des produits de substitution homologués, | M5: 5 les achats ne sont que des achats d’urgence par manque de prévisions. | N5: 0 l’acheteur a toute latitude dans le choix du fournisseur, | O5: 0 il n’y a pas de limite géographique à l’achat, | P5: 4 le changement de fournisseur est long et fastidieux du fait des procédures administratives, | Q5: 5 le défaut de communication interne est à l’origine d’achats réalisés dans des conditions défavorables. | R5: 0 - Nul | S5: 0 - Nul | T5: 1 - Faible | U5: 1 - Faible | V5: 1 - Faible | W5: 0 - Nul | X5: 0 - Nul | Y5: 1 - Faible | Z5: 1 - Faible | AA5: 2 - Modéré | AB5: 0 - Nul | AC5: 1 - Faible | AD5: 1 - Faible | AE5: 1 - Faible | AF5: 0 - Nul | AG5: 2 - Modéré | AH5: 4 - Faible | AI5: Obtenir une expression de besoin du client interne pour savoir si le recours à une centrale d'achat est une option ou s'il faut traiter le dossier en globalité sur un projet de remplacement du matériel obsolète. | AJ5: 2026 | AK5: Faire ou faire faire (externalisation) | AL5: 4 | AM5: 2 | AN5: 9.6 | AO5: 11.2 | AP5: 2.4 | AQ5: 0.8 | AR5: Élément | AS5: sites/DNA948/Lists/Analyse de Portefeuille FINA | AT5: =IFERROR(ROUND(IF(Tableau_query__18[[#This Row],[Sous famille]]<>"",VLOOKUP(Tableau_query__18[[#This Row],[Sous famille]],'A013 TCD'!G:H,2,FALSE),VLOOKUP(Tableau_query__18[[#This Row],[Famille d''achat]],'A013 TCD'!D:E,2,FALSE))/1000,0),"") -> 15
A6: 10 | B6: Informatique & Telecom - Prestations liées aux Progiciels | C6: 45916 | D6: Prestations liées aux Progiciels | E6: Informatique & Telecom | F6: Laurine AUVRAY | H6: 1 les modifications sont minimes et sans conséquence sur l’achat, | I6: 3 entraîne une réduction du nombre de fournisseurs potentiels, | J6: 2 retarde l’achat en l’absence de responsabilité technique, | K6: 1 la forte concurrence amène les fournisseurs à s’adapter, | L6: 5 aucune marge de manœuvre n’est possible. | M6: 1 les prévisions sont relativement satisfaisantes pour couvrir les besoins des acheteurs, | N6: 2 après négociation interne, l’acheteur parvient à qualifier d’autres fournisseurs, | O6: 2 les limites géographiques imposées limitent le choix de fournisseurs, | P6: 4 le changement de fournisseur est long et fastidieux du fait des procédures administratives, | Q6: 1 la communication est suffisante pour les besoins des achats, | R6: 2 - Modéré | S6: 1 - Faible | T6: 2 - Modéré | U6: 1 - Faible | V6: 1 - Faible | W6: 2 - Modéré | X6: 2 - Modéré | Y6: 1 - Faible | Z6: 0 - Nul | AA6: 2 - Modéré | AB6: 0 - Nul | AC6: 0 - Nul | AD6: 1 - Faible | AE6: 1 - Faible | AF6: 0 - Nul | AG6: 0 - Nul | AH6: 1 - Très bon niveau | AI6: Tenter de faire correspondre les dates d'échéance des différents marchés de TMA en cours pour relancer une procédure globale allotie (TMMA, EPM, ORHA, FINA, Portail,...) pour éviter la multiplications des procédures et du temps alloué. | AK6: Faire ou faire faire (externalisation) | AL6: 2 | AM6: 6 | AN6: 9.6 | AO6: 8 | AP6: 8.8 | AQ6: 1.6 | AR6: Élément | AS6: sites/DNA948/Lists/Analyse de Portefeuille FINA | AT6: =IFERROR(ROUND(IF(Tableau_query__18[[#This Row],[Sous famille]]<>"",VLOOKUP(Tableau_query__18[[#This Row],[Sous famille]],'A013 TCD'!G:H,2,FALSE),VLOOKUP(Tableau_query__18[[#This Row],[Famille d''achat]],'A013 TCD'!D:E,2,FALSE))/1000,0),"") -> 3670
A7: 11 | B7: Informatique & Telecom - Prestations liées au matériel et à l'infra | C7: 45918 | D7: Prestations liées au matériel et à l'infra | E7: Informatique & Telecom | F7: Julie GAUJARD | H7: 4 les spécifications sont à l’origine d’une réduction du nombre de fournisseurs potentiel, | I7: 1 de nombreux fournisseurs possèdent le parc requis, | J7: 4 occasionne des achats approximatifs, | K7: 3 entraîne une réduction du nombre de fournisseurs qualifiés, | L7: 5 aucune marge de manœuvre n’est possible. | M7: 5 les achats ne sont que des achats d’urgence par manque de prévisions. | N7: 3 quelques rares fournisseurs imposés peuvent faire l’objet d’une mise en concurrence, | O7: 2 les limites géographiques imposées limitent le choix de fournisseurs, | P7: 4 le changement de fournisseur est long et fastidieux du fait des procédures administratives, | Q7: 5 le défaut de communication interne est à l’origine d’achats réalisés dans des conditions défavorables. | R7: 3 - Important | S7: 0 - Nul | T7: 3 - Important | U7: 1 - Faible | V7: 2 - Modéré | W7: 2 - Modéré | X7: 3 - Important | Y7: 1 - Faible | Z7: 1 - Faible | AA7: 3 - Important | AB7: 0 - Nul | AC7: 1 - Faible | AD7: 2 - Modéré | AE7: 3 - Important | AF7: 0 - Nul | AG7: 0 - Nul | AH7: 2 - Acceptable | AI7: Maintenir la dynamique sur le contrat en cours jusqu'à sa fin. Maintenir le planning de la consultation pour notifier dans les délais. | AJ7: 2025-2026 | AK7: Optimisation du cahier des charges techniques (amélioration des spécifications, cahier des charges fonctionnel) | AL7: 5 | AM7: 7.5 | AN7: 13.6 | AO7: 15.2 | AP7: 6.4 | AQ7: 4.8 | AR7: Élément | AS7: sites/DNA948/Lists/Analyse de Portefeuille FINA | AT7: =IFERROR(ROUND(IF(Tableau_query__18[[#This Row],[Sous famille]]<>"",VLOOKUP(Tableau_query__18[[#This Row],[Sous famille]],'A013 TCD'!G:H,2,FALSE),VLOOKUP(Tableau_query__18[[#This Row],[Famille d''achat]],'A013 TCD'!D:E,2,FALSE))/1000,0),"") -> 4680
A8: 12 | B8: Informatique & Telecom - Poste de travail Informatique | C8: 45916 | D8: Poste de travail Informatique | E8: Informatique & Telecom | F8: Laurine AUVRAY | H8: 2 l’achat n’est remis en question que pour quelques pièces, | I8: 1 de nombreux fournisseurs possèdent le parc requis, | J8: 5 les manques bloquent l’acte d’achat. | K8: 0 la qualité demandée correspond à la moyenne du marché, | L8: 3 oblige à n’acheter que des produits de substitution homologués, | M8: 5 les achats ne sont que des achats d’urgence par manque de prévisions. | N8: 3 quelques rares fournisseurs imposés peuvent faire l’objet d’une mise en concurrence, | O8: 0 il n’y a pas de limite géographique à l’achat, | P8: 4 le changement de fournisseur est long et fastidieux du fait des procédures administratives, | Q8: 5 le défaut de communication interne est à l’origine d’achats réalisés dans des conditions défavorables. | R8: 1 - Faible | S8: 1 - Faible | T8: 1 - Faible | U8: 3 - Important | V8: 1 - Faible | W8: 1 - Faible | X8: 2 - Modéré | Y8: 3 - Important | Z8: 3 - Important | AA8: 3 - Important | AB8: 1 - Faible | AC8: 2 - Modéré | AD8: 2 - Modéré | AE8: 2 - Modéré | AF8: 2 - Modéré | AG8: 4 - Majeur | AH8: 2 - Acceptable | AI8: Recourir à une centrale d'achat pour s'approvisionner car achats simples | AJ8: T4 2025 | AK8: Faire ou faire faire (externalisation) | AL8: 9.5 | AM8: 6.5 | AN8: 8.8 | AO8: 13.6 | AP8: 2.4 | AQ8: 5.6 | AR8: Élément | AS8: sites/DNA948/Lists/Analyse de Portefeuille FINA | AT8: =IFERROR(ROUND(IF(Tableau_query__18[[#This Row],[Sous famille]]<>"",VLOOKUP(Tableau_query__18[[#This Row],[Sous famille]],'A013 TCD'!G:H,2,FALSE),VLOOKUP(Tableau_query__18[[#This Row],[Famille d''achat]],'A013 TCD'!D:E,2,FALSE))/1000,0),"") -> 1445
A9: 13 | B9: Informatique & Telecom - Périphériques et accessoires informatiques | C9: 45916 | D9: Périphériques et accessoires informatiques | E9: Informatique & Telecom | F9: Laurine AUVRAY | H9: 0 elles rejoignent nos propres spécifications, | I9: 0 égale à la moyenne du secteur, | J9: 2 retarde l’achat en l’absence de responsabilité technique, | K9: 0 la qualité demandée correspond à la moyenne du marché, | L9: 0 aucune difficulté pour recourir à des produits de substitution, | M9: 1 les prévisions sont relativement satisfaisantes pour couvrir les besoins des acheteurs, | N9: 0 l’acheteur a toute latitude dans le choix du fournisseur, | O9: 0 il n’y a pas de limite géographique à l’achat, | P9: 1 le circuit administratif retarde les modifications de dossiers d’achat, | Q9: 3 la communication ne permet pas d’anticiper les besoins, | R9: 0 - Nul | S9: 1 - Faible | T9: 2 - Modéré | U9: 2 - Modéré | V9: 1 - Faible | W9: 1 - Faible | X9: 1 - Faible | Y9: 2 - Modéré | Z9: 2 - Modéré | AA9: 2 - Modéré | AB9: 1 - Faible | AC9: 1 - Faible | AD9: 2 - Modéré | AE9: 1 - Faible | AF9: 2 - Modéré | AG9: 3 - Important | AH9: 0 - Sécurisé | AI9: Recourir à une centrale d'achat pour s'approvisionner car achats simples | AJ9: 2025 | AL9: 7 | AM9: 5 | AN9: 1.6 | AO9: 0 | AP9: 0 | AQ9: 0 | AR9: Élément | AS9: sites/DNA948/Lists/Analyse de Portefeuille FINA | AT9: =IFERROR(ROUND(IF(Tableau_query__18[[#This Row],[Sous famille]]<>"",VLOOKUP(Tableau_query__18[[#This Row],[Sous famille]],'A013 TCD'!G:H,2,FALSE),VLOOKUP(Tableau_query__18[[#This Row],[Famille d''achat]],'A013 TCD'!D:E,2,FALSE))/1000,0),"") -> 645
A10: 14 | B10: Informatique & Telecom - Matériels et accessoires de télécommunication | C10: 45918 | D10: Matériels et accessoires de télécommunication | E10: Informatique & Telecom | F10: Julie GAUJARD | AL10: 0 | AM10: 0 | AN10: 0 | AO10: 0 | AP10: 0 | AQ10: 0 | AR10: Élément | AS10: sites/DNA948/Lists/Analyse de Portefeuille FINA | AT10: =IFERROR(ROUND(IF(Tableau_query__18[[#This Row],[Sous famille]]<>"",VLOOKUP(Tableau_query__18[[#This Row],[Sous famille]],'A013 TCD'!G:H,2,FALSE),VLOOKUP(Tableau_query__18[[#This Row],[Famille d''achat]],'A013 TCD'!D:E,2,FALSE))/1000,0),"") -> 34
A11: 15 | B11: Informatique & Telecom - Logiciels | C11: 45916 | D11: Logiciels | E11: Informatique & Telecom | F11: Laurine AUVRAY | H11: 1 les modifications sont minimes et sans conséquence sur l’achat, | I11: 4 oblige à recourir à plusieurs fournisseurs ou sous-traitants, | J11: 3 reporte l’achat à cause d’une refonte nécessaire du dossier technique, | K11: 0 la qualité demandée correspond à la moyenne du marché, | L11: 3 oblige à n’acheter que des produits de substitution homologués, | M11: 5 les achats ne sont que des achats d’urgence par manque de prévisions. | N11: 3 quelques rares fournisseurs imposés peuvent faire l’objet d’une mise en concurrence, | O11: 0 il n’y a pas de limite géographique à l’achat, | P11: 4 le changement de fournisseur est long et fastidieux du fait des procédures administratives, | Q11: 4 le défaut de communication interne crée un frein à l’étude du marché, | R11: 0 - Nul | S11: 0 - Nul | T11: 0 - Nul | U11: 0 - Nul | V11: 1 - Faible | W11: 0 - Nul | X11: 1 - Faible | Y11: 2 - Modéré | Z11: 2 - Modéré | AA11: 2 - Modéré | AB11: 0 - Nul | AC11: 1 - Faible | AD11: 1 - Faible | AE11: 1 - Faible | AF11: 0 - Nul | AG11: 0 - Nul | AH11: 0 - Sécurisé | AI11: Obtenir une liste complète des besoins fournie par la DSI et la DII | AJ11: T3 2027 | AL11: 3.5 | AM11: 2 | AN11: 8.8 | AO11: 0 | AP11: 2.4 | AQ11: 1.6 | AR11: Élément | AS11: sites/DNA948/Lists/Analyse de Portefeuille FINA | AT11: =IFERROR(ROUND(IF(Tableau_query__18[[#This Row],[Sous famille]]<>"",VLOOKUP(Tableau_query__18[[#This Row],[Sous famille]],'A013 TCD'!G:H,2,FALSE),VLOOKUP(Tableau_query__18[[#This Row],[Famille d''achat]],'A013 TCD'!D:E,2,FALSE))/1000,0),"") -> 6669
A12: 16 | B12: Informatique & Telecom - E-learning | C12: 45918 | D12: E-learning | E12: Informatique & Telecom | F12: Laurine AUVRAY | H12: 4 les spécifications sont à l’origine d’une réduction du nombre de fournisseurs potentiel, | I12: 3 entraîne une réduction du nombre de fournisseurs potentiels, | J12: 4 occasionne des achats approximatifs, | K12: 4 est à l’origine d’un marché fermé (1 acheteur et 1 vendeur), | L12: 4 oblige à négocier âprement avec le fabricant retenu par les services techniques, | M12: 1 les prévisions sont relativement satisfaisantes pour couvrir les besoins des acheteurs, | N12: 0 l’acheteur a toute latitude dans le choix du fournisseur, | O12: 1 les limites géographiques imposées n’entraînent pas de frein à l’achat, | P12: 4 le changement de fournisseur est long et fastidieux du fait des procédures administratives, | Q12: 2 les contacts sont rares avec les services non directement concernés par l’acte d’achat, | R12: 3 - Important | S12: 2 - Modéré | T12: 2 - Modéré | U12: 1 - Faible | V12: 1 - Faible | W12: 2 - Modéré | X12: 2 - Modéré | Y12: 2 - Modéré | Z12: 1 - Faible | AA12: 2 - Modéré | AB12: 2 - Modéré | AC12: 0 - Nul | AD12: 1 - Faible | AE12: 1 - Faible | AF12: 1 - Faible | AG12: 1 - Faible | AH12: 0 - Sécurisé | AI12: Mieux travailler le cahier des charges par le client interne pour optimiser la concurrence | AJ12: 2028 | AK12: Optimisation du cahier des charges techniques (amélioration des spécifications, cahier des charges fonctionnel) | AL12: 4.5 | AM12: 7.5 | AN12: 15.2 | AO12: 6.4 | AP12: 4 | AQ12: 1.6 | AR12: Élément | AS12: sites/DNA948/Lists/Analyse de Portefeuille FINA | AT12: =IFERROR(ROUND(IF(Tableau_query__18[[#This Row],[Sous famille]]<>"",VLOOKUP(Tableau_query__18[[#This Row],[Sous famille]],'A013 TCD'!G:H,2,FALSE),VLOOKUP(Tableau_query__18[[#This Row],[Famille d''achat]],'A013 TCD'!D:E,2,FALSE))/1000,0),"") -> 117
A13: 17 | B13: Informatique & Telecom - Datacenter et Cloud | C13: 45918 | D13: Datacenter et Cloud | E13: Informatique & Telecom | F13: Julie GAUJARD | H13: 4 les spécifications sont à l’origine d’une réduction du nombre de fournisseurs potentiel, | I13: 1 de nombreux fournisseurs possèdent le parc requis, | J13: 4 occasionne des achats approximatifs, | K13: 3 entraîne une réduction du nombre de fournisseurs qualifiés, | L13: 5 aucune marge de manœuvre n’est possible. | M13: 5 les achats ne sont que des achats d’urgence par manque de prévisions. | N13: 3 quelques rares fournisseurs imposés peuvent faire l’objet d’une mise en concurrence, | O13: 2 les limites géographiques imposées limitent le choix de fournisseurs, | P13: 4 le changement de fournisseur est long et fastidieux du fait des procédures administratives, | Q13: 5 le défaut de communication interne est à l’origine d’achats réalisés dans des conditions défavorables. | R13: 4 - Majeur | S13: 0 - Nul | T13: 3 - Important | U13: 1 - Faible | V13: 2 - Modéré | W13: 4 - Majeur | X13: 2 - Modéré | Y13: 1 - Faible | Z13: 1 - Faible | AA13: 3 - Important | AB13: 0 - Nul | AC13: 1 - Faible | AD13: 2 - Modéré | AE13: 3 - Important | AF13: 0 - Nul | AG13: 0 - Nul | AH13: 2 - Acceptable | AI13: Maintenir la dynamique sur le contrat en cours jusqu'à sa fin. Maintenir le planning de la consultation pour notifier dans les délais. | AJ13: 2025-2026 | AK13: Optimisation du cahier des charges techniques (amélioration des spécifications, cahier des charges fonctionnel) | AL13: 5 | AM13: 8.5 | AN13: 13.6 | AO13: 15.2 | AP13: 6.4 | AQ13: 3.2 | AR13: Élément | AS13: sites/DNA948/Lists/Analyse de Portefeuille FINA | AT13: =IFERROR(ROUND(IF(Tableau_query__18[[#This Row],[Sous famille]]<>"",VLOOKUP(Tableau_query__18[[#This Row],[Sous famille]],'A013 TCD'!G:H,2,FALSE),VLOOKUP(Tableau_query__18[[#This Row],[Famille d''achat]],'A013 TCD'!D:E,2,FALSE))/1000,0),"") -> 3582
A14: 18 | B14: Informatique & Telecom - Conseil et audit | C14: 45916 | D14: Conseil et audit | E14: Informatique & Telecom | F14: Laurine AUVRAY | H14: 1 les modifications sont minimes et sans conséquence sur l’achat, | I14: 1 de nombreux fournisseurs possèdent le parc requis, | J14: 4 occasionne des achats approximatifs, | K14: 1 la forte concurrence amène les fournisseurs à s’adapter, | L14: 0 aucune difficulté pour recourir à des produits de substitution, | M14: 4 les prévisions n’existent qu’à court terme et ont donc un impact moindre auprès des fournisseurs, | N14: 0 l’acheteur a toute latitude dans le choix du fournisseur, | O14: 2 les limites géographiques imposées limitent le choix de fournisseurs, | P14: 4 le changement de fournisseur est long et fastidieux du fait des procédures administratives, | Q14: 3 la communication ne permet pas d’anticiper les besoins, | R14: 0 - Nul | S14: 0 - Nul | T14: 2 - Modéré | U14: 0 - Nul | V14: 3 - Important | W14: 0 - Nul | X14: 2 - Modéré | Y14: 3 - Important | Z14: 1 - Faible | AA14: 2 - Modéré | AB14: 0 - Nul | AC14: 1 - Faible | AD14: 0 - Nul | AE14: 2 - Modéré | AF14: 0 - Nul | AG14: 0 - Nul | AH14: 1 - Très bon niveau | AI14: Prévoir le type de renouvellement (subséquents avec classement, remise en concurrence...?). Le client interne est-il capable de nous fournir une programmation des besoins à venir. | AJ14: T2 2026 | AL14: 3 | AM14: 5 | AN14: 5.6 | AO14: 0 | AP14: 0 | AQ14: 0 | AR14: Élément | AS14: sites/DNA948/Lists/Analyse de Portefeuille FINA | AT14: =IFERROR(ROUND(IF(Tableau_query__18[[#This Row],[Sous famille]]<>"",VLOOKUP(Tableau_query__18[[#This Row],[Sous famille]],'A013 TCD'!G:H,2,FALSE),VLOOKUP(Tableau_query__18[[#This Row],[Famille d''achat]],'A013 TCD'!D:E,2,FALSE))/1000,0),"") -> 4524
A15: 19 | B15: Matériels - Solier | C15: 45938 | D15: Solier | E15: Matériels | F15: Jérôme CORTES | AL15: 0 | AM15: 0 | AN15: 0 | AO15: 0 | AP15: 0 | AQ15: 0 | AR15: Élément | AS15: sites/DNA948/Lists/Analyse de Portefeuille FINA | AT15: =IFERROR(ROUND(IF(Tableau_query__18[[#This Row],[Sous famille]]<>"",VLOOKUP(Tableau_query__18[[#This Row],[Sous famille]],'A013 TCD'!G:H,2,FALSE),VLOOKUP(Tableau_query__18[[#This Row],[Famille d''achat]],'A013 TCD'!D:E,2,FALSE))/1000,0),"") -> 241
A16: 20 | B16: Matériels - Quincaillerie d assemblage | D16: Quincaillerie d assemblage | E16: Matériels | F16: Laurent AGBOTON | AR16: Élément | AS16: sites/DNA948/Lists/Analyse de Portefeuille FINA | AT16: =IFERROR(ROUND(IF(Tableau_query__18[[#This Row],[Sous famille]]<>"",VLOOKUP(Tableau_query__18[[#This Row],[Sous famille]],'A013 TCD'!G:H,2,FALSE),VLOOKUP(Tableau_query__18[[#This Row],[Famille d''achat]],'A013 TCD'!D:E,2,FALSE))/1000,0),"") -> 140
A17: 21 | B17: Matériels - Quincaillerie d ameublement | D17: Quincaillerie d ameublement | E17: Matériels | F17: Laurent AGBOTON | AR17: Élément | AS17: sites/DNA948/Lists/Analyse de Portefeuille FINA | AT17: =IFERROR(ROUND(IF(Tableau_query__18[[#This Row],[Sous famille]]<>"",VLOOKUP(Tableau_query__18[[#This Row],[Sous famille]],'A013 TCD'!G:H,2,FALSE),VLOOKUP(Tableau_query__18[[#This Row],[Famille d''achat]],'A013 TCD'!D:E,2,FALSE))/1000,0),"") -> 243
A18: 22 | B18: Matériels - Produits métallurgiques hors bâtiment | C18: 45979 | D18: Produits métallurgiques hors bâtiment | E18: Matériels | F18: Guy HORNUNG | H18: 1 les modifications sont minimes et sans conséquence sur l’achat, | I18: 3 entraîne une réduction du nombre de fournisseurs potentiels, | J18: 1 les précisions nécessaires au fournisseur peuvent être obtenues sans difficulté, | L18: 5 aucune marge de manœuvre n’est possible. | M18: 0 les prévisions à moyen et long terme sont fiables, | N18: 0 l’acheteur a toute latitude dans le choix du fournisseur, | O18: 0 il n’y a pas de limite géographique à l’achat, | P18: 0 pas de lourdeur administrative, | Q18: 1 la communication est suffisante pour les besoins des achats, | T18: 2 - Modéré | U18: 2 - Modéré | V18: 0 - Nul | X18: 1 - Faible | Y18: 1 - Faible | Z18: 1 - Faible | AC18: 2 - Modéré | AD18: 1 - Faible | AE18: 3 - Important | AG18: 1 - Faible | AH18: 0 - Sécurisé | AI18: Lancement d'un AO en regroupant les Produits métallurgiques du Bâtiment | AJ18: 2028/2029 | AK18: Conception à coût objectif (CCO) | AL18: 4 | AM18: 3 | AN18: 8 | AO18: 0.8 | AP18: 4 | AQ18: 0 | AR18: Élément | AS18: sites/DNA948/Lists/Analyse de Portefeuille FINA | AT18: =IFERROR(ROUND(IF(Tableau_query__18[[#This Row],[Sous famille]]<>"",VLOOKUP(Tableau_query__18[[#This Row],[Sous famille]],'A013 TCD'!G:H,2,FALSE),VLOOKUP(Tableau_query__18[[#This Row],[Famille d''achat]],'A013 TCD'!D:E,2,FALSE))/1000,0),"") -> 738
A19: 23 | B19: Matériels - Produits d'hygiène et de nettoyage | D19: Produits d'hygiène et de nettoyage | E19: Matériels | F19: Laurent AGBOTON | AR19: Élément | AS19: sites/DNA948/Lists/Analyse de Portefeuille FINA | AT19: =IFERROR(ROUND(IF(Tableau_query__18[[#This Row],[Sous famille]]<>"",VLOOKUP(Tableau_query__18[[#This Row],[Sous famille]],'A013 TCD'!G:H,2,FALSE),VLOOKUP(Tableau_query__18[[#This Row],[Famille d''achat]],'A013 TCD'!D:E,2,FALSE))/1000,0),"") -> 231
A20: 24 | B20: Matériels - Produit métallurgique du bâtiment | D20: Produit métallurgique du bâtiment | E20: Matériels | F20: Jérôme CORTES | AL20: 0 | AM20: 0 | AN20: 0 | AO20: 0 | AP20: 0 | AQ20: 0 | AR20: Élément | AS20: sites/DNA948/Lists/Analyse de Portefeuille FINA | AT20: =IFERROR(ROUND(IF(Tableau_query__18[[#This Row],[Sous famille]]<>"",VLOOKUP(Tableau_query__18[[#This Row],[Sous famille]],'A013 TCD'!G:H,2,FALSE),VLOOKUP(Tableau_query__18[[#This Row],[Famille d''achat]],'A013 TCD'!D:E,2,FALSE))/1000,0),"") -> 65
A21: 25 | B21: Matériels - Plaquiste | D21: Plaquiste | E21: Matériels | F21: Jérôme CORTES | AR21: Élément | AS21: sites/DNA948/Lists/Analyse de Portefeuille FINA | AT21: =IFERROR(ROUND(IF(Tableau_query__18[[#This Row],[Sous famille]]<>"",VLOOKUP(Tableau_query__18[[#This Row],[Sous famille]],'A013 TCD'!G:H,2,FALSE),VLOOKUP(Tableau_query__18[[#This Row],[Famille d''achat]],'A013 TCD'!D:E,2,FALSE))/1000,0),"") -> 988
A22: 26 | B22: Matériels - Peinture et revêtements muraux | D22: Peinture et revêtements muraux | E22: Matériels | F22: Jérôme CORTES | AR22: Élément | AS22: sites/DNA948/Lists/Analyse de Portefeuille FINA | AT22: =IFERROR(ROUND(IF(Tableau_query__18[[#This Row],[Sous famille]]<>"",VLOOKUP(Tableau_query__18[[#This Row],[Sous famille]],'A013 TCD'!G:H,2,FALSE),VLOOKUP(Tableau_query__18[[#This Row],[Famille d''achat]],'A013 TCD'!D:E,2,FALSE))/1000,0),"") -> 570
A23: 27 | B23: Matériels - Outils pneumatiques | D23: Outils pneumatiques | E23: Matériels | F23: Laurent AGBOTON | AR23: Élément | AS23: sites/DNA948/Lists/Analyse de Portefeuille FINA | AT23: =IFERROR(ROUND(IF(Tableau_query__18[[#This Row],[Sous famille]]<>"",VLOOKUP(Tableau_query__18[[#This Row],[Sous famille]],'A013 TCD'!G:H,2,FALSE),VLOOKUP(Tableau_query__18[[#This Row],[Famille d''achat]],'A013 TCD'!D:E,2,FALSE))/1000,0),"") -> 11
A24: 28 | B24: Matériels - Outils coupants | D24: Outils coupants | E24: Matériels | F24: Laurent AGBOTON | AR24: Élément | AS24: sites/DNA948/Lists/Analyse de Portefeuille FINA | AT24: =IFERROR(ROUND(IF(Tableau_query__18[[#This Row],[Sous famille]]<>"",VLOOKUP(Tableau_query__18[[#This Row],[Sous famille]],'A013 TCD'!G:H,2,FALSE),VLOOKUP(Tableau_query__18[[#This Row],[Famille d''achat]],'A013 TCD'!D:E,2,FALSE))/1000,0),"") -> 108
A25: 29 | B25: Matériels - Outillage à mains | D25: Outillage à mains | E25: Matériels | F25: Laurent AGBOTON | AR25: Élément | AS25: sites/DNA948/Lists/Analyse de Portefeuille FINA | AT25: =IFERROR(ROUND(IF(Tableau_query__18[[#This Row],[Sous famille]]<>"",VLOOKUP(Tableau_query__18[[#This Row],[Sous famille]],'A013 TCD'!G:H,2,FALSE),VLOOKUP(Tableau_query__18[[#This Row],[Famille d''achat]],'A013 TCD'!D:E,2,FALSE))/1000,0),"") -> 673
A26: 30 | B26: Matériels - Monteurs de réseau | D26: Monteurs de réseau | E26: Matériels | F26: Jérôme CORTES | AR26: Élément | AS26: sites/DNA948/Lists/Analyse de Portefeuille FINA | AT26: =IFERROR(ROUND(IF(Tableau_query__18[[#This Row],[Sous famille]]<>"",VLOOKUP(Tableau_query__18[[#This Row],[Sous famille]],'A013 TCD'!G:H,2,FALSE),VLOOKUP(Tableau_query__18[[#This Row],[Famille d''achat]],'A013 TCD'!D:E,2,FALSE))/1000,0),"") -> 269
A27: 31 | B27: Matériels - Mobilier de bureau d'accueil et accessoire | D27: Mobilier de bureau d'accueil et accessoire | E27: Matériels | F27: Laurent AGBOTON | AR27: Élément | AS27: sites/DNA948/Lists/Analyse de Portefeuille FINA | AT27: =IFERROR(ROUND(IF(Tableau_query__18[[#This Row],[Sous famille]]<>"",VLOOKUP(Tableau_query__18[[#This Row],[Sous famille]],'A013 TCD'!G:H,2,FALSE),VLOOKUP(Tableau_query__18[[#This Row],[Famille d''achat]],'A013 TCD'!D:E,2,FALSE))/1000,0),"") -> 482
A28: 32 | B28: Matériels - Matériels de surveillance | D28: Matériels de surveillance | E28: Matériels | F28: Jérôme CORTES | AR28: Élément | AS28: sites/DNA948/Lists/Analyse de Portefeuille FINA | AT28: =IFERROR(ROUND(IF(Tableau_query__18[[#This Row],[Sous famille]]<>"",VLOOKUP(Tableau_query__18[[#This Row],[Sous famille]],'A013 TCD'!G:H,2,FALSE),VLOOKUP(Tableau_query__18[[#This Row],[Famille d''achat]],'A013 TCD'!D:E,2,FALSE))/1000,0),"") -> 293
A29: 33 | B29: Matériels - Maçonnerie VRD | D29: Maçonnerie VRD | E29: Matériels | F29: Jérôme CORTES | AR29: Élément | AS29: sites/DNA948/Lists/Analyse de Portefeuille FINA | AT29: =IFERROR(ROUND(IF(Tableau_query__18[[#This Row],[Sous famille]]<>"",VLOOKUP(Tableau_query__18[[#This Row],[Sous famille]],'A013 TCD'!G:H,2,FALSE),VLOOKUP(Tableau_query__18[[#This Row],[Famille d''achat]],'A013 TCD'!D:E,2,FALSE))/1000,0),"") -> 1262
A30: 34 | B30: Matériels - Isolation Thermique par l'Extérieur | D30: Isolation Thermique par l'Extérieur | E30: Matériels | F30: Jérôme CORTES | AR30: Élément | AS30: sites/DNA948/Lists/Analyse de Portefeuille FINA | AT30: =IFERROR(ROUND(IF(Tableau_query__18[[#This Row],[Sous famille]]<>"",VLOOKUP(Tableau_query__18[[#This Row],[Sous famille]],'A013 TCD'!G:H,2,FALSE),VLOOKUP(Tableau_query__18[[#This Row],[Famille d''achat]],'A013 TCD'!D:E,2,FALSE))/1000,0),"") -> 125
A31: 35 | B31: Matériels - Gaz industriels | D31: Gaz industriels | E31: Matériels | F31: Guy HORNUNG | AR31: Élément | AS31: sites/DNA948/Lists/Analyse de Portefeuille FINA | AT31: =IFERROR(ROUND(IF(Tableau_query__18[[#This Row],[Sous famille]]<>"",VLOOKUP(Tableau_query__18[[#This Row],[Sous famille]],'A013 TCD'!G:H,2,FALSE),VLOOKUP(Tableau_query__18[[#This Row],[Famille d''achat]],'A013 TCD'!D:E,2,FALSE))/1000,0),"") -> 1265
A32: 36 | B32: Matériels - Fournitures nautiques et aéronautiques | D32: Fournitures nautiques et aéronautiques | E32: Matériels | F32: Guy HORNUNG | AR32: Élément | AS32: sites/DNA948/Lists/Analyse de Portefeuille FINA | AT32: =IFERROR(ROUND(IF(Tableau_query__18[[#This Row],[Sous famille]]<>"",VLOOKUP(Tableau_query__18[[#This Row],[Sous famille]],'A013 TCD'!G:H,2,FALSE),VLOOKUP(Tableau_query__18[[#This Row],[Famille d''achat]],'A013 TCD'!D:E,2,FALSE))/1000,0),"") -> 224
... A59: 63 | B59: Prestations - Véhicule de service et de fonction | D59: Véhicule de service et de fonction | E59: Prestations | F59: Stéphane DELATOUR | AR59: Élément | AS59: sites/DNA948/Lists/Analyse de Portefeuille FINA | AT59: =IFERROR(ROUND(IF(Tableau_query__18[[#This Row],[Sous famille]]<>"",VLOOKUP(Tableau_query__18[[#This Row],[Sous famille]],'A013 TCD'!G:H,2,FALSE),VLOOKUP(Tableau_query__18[[#This Row],[Famille d''achat]],'A013 TCD'!D:E,2,FALSE))/1000,0),"") -> 7437
A60: 64 | B60: Prestations - Transport de personnes | C60: 46030 | D60: Transport de personnes | E60: Prestations | F60: Cindy CHUNE | H60: 1 les modifications sont minimes et sans conséquence sur l’achat, | I60: 1 de nombreux fournisseurs possèdent le parc requis, | J60: 1 les précisions nécessaires au fournisseur peuvent être obtenues sans difficulté, | K60: 0 la qualité demandée correspond à la moyenne du marché, | L60: 0 aucune difficulté pour recourir à des produits de substitution, | M60: 1 les prévisions sont relativement satisfaisantes pour couvrir les besoins des acheteurs, | N60: 0 l’acheteur a toute latitude dans le choix du fournisseur, | O60: 2 les limites géographiques imposées limitent le choix de fournisseurs, | P60: 0 pas de lourdeur administrative, | Q60: 1 la communication est suffisante pour les besoins des achats, | R60: 1 - Faible | S60: 0 - Nul | T60: 1 - Faible | U60: 1 - Faible | V60: 0 - Nul | W60: 0 - Nul | X60: 3 - Important | Y60: 3 - Important | Z60: 3 - Important | AA60: 2 - Modéré | AB60: 0 - Nul | AC60: 0 - Nul | AD60: 2 - Modéré | AE60: 1 - Faible | AF60: 1 - Faible | AG60: 1 - Faible | AH60: 0 - Sécurisé | AI60: Le Marché CAP 5 couvre 38% sur 80 000€ ed dépenses en 2025 (location véhicule courte durée ou transport en commun avion,train,..). Les autres dépenses sont des locations de bus avec chauffeur pour transport de stagiaires (40 000€ environ). Le nouveaux seuil du MAPA étant porté à 60 000€, il ne sera pas réalisé de marché spécifique . | AL60: 4.5 | AM60: 4.5 | AN60: 2.4 | AO60: 3.2 | AP60: 0.8 | AQ60: 0 | AR60: Élément | AS60: sites/DNA948/Lists/Analyse de Portefeuille FINA | AT60: =IFERROR(ROUND(IF(Tableau_query__18[[#This Row],[Sous famille]]<>"",VLOOKUP(Tableau_query__18[[#This Row],[Sous famille]],'A013 TCD'!G:H,2,FALSE),VLOOKUP(Tableau_query__18[[#This Row],[Famille d''achat]],'A013 TCD'!D:E,2,FALSE))/1000,0),"") -> 95
A61: 65 | B61: Prestations - Signalétique | D61: Signalétique | E61: Prestations | F61: Smahan EL MALAH | AR61: Élément | AS61: sites/DNA948/Lists/Analyse de Portefeuille FINA | AT61: =IFERROR(ROUND(IF(Tableau_query__18[[#This Row],[Sous famille]]<>"",VLOOKUP(Tableau_query__18[[#This Row],[Sous famille]],'A013 TCD'!G:H,2,FALSE),VLOOKUP(Tableau_query__18[[#This Row],[Famille d''achat]],'A013 TCD'!D:E,2,FALSE))/1000,0),"") -> 186
A62: 66 | B62: Prestations - Services liés aux déchets et ordures | C62: 45958 | D62: Services liés aux déchets et ordures | E62: Prestations | F62: Karine FANTINI | H62: 3 les spécifications obligent à des renégociations avec les fournisseurs, | I62: 1 de nombreux fournisseurs possèdent le parc requis, | J62: 4 occasionne des achats approximatifs, | L62: 5 aucune marge de manœuvre n’est possible. | M62: 3 les prévisions sont aléatoires, ce qui est préjudiciable aux négociations, | N62: 0 l’acheteur a toute latitude dans le choix du fournisseur, | O62: 2 les limites géographiques imposées limitent le choix de fournisseurs, | P62: 2 les lourdeurs administratives occasionnent des retards de paiement des fournisseurs, | Q62: 1 la communication est suffisante pour les besoins des achats, | T62: 2 - Modéré | U62: 2 - Modéré | V62: 3 - Important | X62: 3 - Important | Y62: 1 - Faible | Z62: 3 - Important | AC62: 3 - Important | AD62: 1 - Faible | AE62: 3 - Important | AG62: 5 - Extrême | AH62: 1 - Très bon niveau | AI62: Revoir le BPU et désignation d'articles obsolescents. Fiabiliser les DQE. Revoir l'allotissement : actuellement en grandes régions, génère de la sous-traitance et des coûts de transport plus élevés. Prévoir un allotissement en mode "territoire" (Regroupement de plusieurs Sites Afpa au plus près des centres de tri), surtout pour les déchets spéciaux | AJ62: 2027 S1 | AL62: 0 | AM62: 5.5 | AN62: 10.4 | AO62: 0 | AP62: 4 | AQ62: 0 | AR62: Élément | AS62: sites/DNA948/Lists/Analyse de Portefeuille FINA | AT62: =IFERROR(ROUND(IF(Tableau_query__18[[#This Row],[Sous famille]]<>"",VLOOKUP(Tableau_query__18[[#This Row],[Sous famille]],'A013 TCD'!G:H,2,FALSE),VLOOKUP(Tableau_query__18[[#This Row],[Famille d''achat]],'A013 TCD'!D:E,2,FALSE))/1000,0),"") -> 3184
A63: 67 | B63: Prestations - Services financiers et d'assurances | C63: 46106 | D63: Services financiers et d'assurances | E63: Prestations | F63: Nathalie CORMIER | H63: 3 les spécifications obligent à des renégociations avec les fournisseurs, | I63: 3 entraîne une réduction du nombre de fournisseurs potentiels, | J63: 2 retarde l’achat en l’absence de responsabilité technique, | K63: 3 entraîne une réduction du nombre de fournisseurs qualifiés, | L63: 5 aucune marge de manœuvre n’est possible. | M63: 1 les prévisions sont relativement satisfaisantes pour couvrir les besoins des acheteurs, | N63: 1 les impositions correspondent au meilleur choix, | O63: 1 les limites géographiques imposées n’entraînent pas de frein à l’achat, | P63: 3 le circuit administratif engendre des litiges avec les fournisseurs, | Q63: 2 les contacts sont rares avec les services non directement concernés par l’acte d’achat, | R63: 2 - Modéré | S63: 2 - Modéré | T63: 0 - Nul | U63: 3 - Important | V63: 2 - Modéré | W63: 0 - Nul | X63: 1 - Faible | Y63: 1 - Faible | Z63: 1 - Faible | AA63: 1 - Faible | AC63: 1 - Faible | AD63: 1 - Faible | AE63: 1 - Faible | AF63: 1 - Faible | AG63: 1 - Faible | AH63: 1 - Très bon niveau | AI63: 2026-2027 :Remise en concurrence des marchés d'assurances qui couvrent 97% du CA. Les 3 % restants correspponde aux franchises qui sont directement payés aux garagistes. Ana lyse d'opportunité pour envisager de faire appel au RESAH (courtieravec une mission de recherche de solutions assurantielles et UGAP (assurance voiture) | AJ63: 2027 | AK63: Faire ou faire faire (externalisation) | AL63: 0 | AM63: 0 | AN63: 12.8 | AO63: 6.4 | AP63: 2.4 | AQ63: 8.8 | AR63: Élément | AS63: sites/DNA948/Lists/Analyse de Portefeuille FINA | AT63: =IFERROR(ROUND(IF(Tableau_query__18[[#This Row],[Sous famille]]<>"",VLOOKUP(Tableau_query__18[[#This Row],[Sous famille]],'A013 TCD'!G:H,2,FALSE),VLOOKUP(Tableau_query__18[[#This Row],[Famille d''achat]],'A013 TCD'!D:E,2,FALSE))/1000,0),"") -> 2485
A64: 68 | B64: Prestations - Services divers | D64: Services divers | E64: Prestations | F64: Smahan EL MALAH | AR64: Élément | AS64: sites/DNA948/Lists/Analyse de Portefeuille FINA | AT64: =IFERROR(ROUND(IF(Tableau_query__18[[#This Row],[Sous famille]]<>"",VLOOKUP(Tableau_query__18[[#This Row],[Sous famille]],'A013 TCD'!G:H,2,FALSE),VLOOKUP(Tableau_query__18[[#This Row],[Famille d''achat]],'A013 TCD'!D:E,2,FALSE))/1000,0),"") -> 5
A65: 69 | B65: Prestations - Services d'Impression, de publication et services connexes | C65: 46111 | D65: Services d'Impression, de publication et services connexes | E65: Prestations | F65: Cindy CHUNE | H65: 4 les spécifications sont à l’origine d’une réduction du nombre de fournisseurs potentiel, | I65: 1 de nombreux fournisseurs possèdent le parc requis, | J65: 2 retarde l’achat en l’absence de responsabilité technique, | K65: 0 la qualité demandée correspond à la moyenne du marché, | L65: 0 aucune difficulté pour recourir à des produits de substitution, | M65: 4 les prévisions n’existent qu’à court terme et ont donc un impact moindre auprès des fournisseurs, | N65: 2 après négociation interne, l’acheteur parvient à qualifier d’autres fournisseurs, | O65: 1 les limites géographiques imposées n’entraînent pas de frein à l’achat, | P65: 1 le circuit administratif retarde les modifications de dossiers d’achat, | Q65: 4 le défaut de communication interne crée un frein à l’étude du marché, | R65: 1 - Faible | S65: 0 - Nul | T65: 1 - Faible | U65: 1 - Faible | V65: 0 - Nul | W65: 1 - Faible | X65: 3 - Important | Y65: 3 - Important | Z65: 2 - Modéré | AA65: 3 - Important | AB65: 2 - Modéré | AC65: 2 - Modéré | AD65: 2 - Modéré | AE65: 2 - Modéré | AF65: 3 - Important | AG65: 2 - Modéré | AH65: 5 - Critique | AI65: Mettre en place un marché multi service pour couvrir l'ensemble du processus impressions et services connexes comme la numérisation, le façonnage, etc. | AJ65: 2026 | AK65: Harmonisation, standardisation de l'achat | AL65: 9 | AM65: 5 | AN65: 5.6 | AO65: 9.6 | AP65: 1.6 | AQ65: 0 | AR65: Élément | AS65: sites/DNA948/Lists/Analyse de Portefeuille FINA | AT65: =IFERROR(ROUND(IF(Tableau_query__18[[#This Row],[Sous famille]]<>"",VLOOKUP(Tableau_query__18[[#This Row],[Sous famille]],'A013 TCD'!G:H,2,FALSE),VLOOKUP(Tableau_query__18[[#This Row],[Famille d''achat]],'A013 TCD'!D:E,2,FALSE))/1000,0),"") -> 111
A66: 70 | B66: Prestations - Services d'entretien d'ascenseurs et de monte-charges portes et portails | C66: 45959 | D66: Services d'entretien d'ascenseurs et de monte-charges | E66: Prestations | F66: Karine FANTINI | H66: 0 elles rejoignent nos propres spécifications, | I66: 1 de nombreux fournisseurs possèdent le parc requis, | J66: 1 les précisions nécessaires au fournisseur peuvent être obtenues sans difficulté, | L66: 5 aucune marge de manœuvre n’est possible. | M66: 0 les prévisions à moyen et long terme sont fiables, | N66: 0 l’acheteur a toute latitude dans le choix du fournisseur, | O66: 1 les limites géographiques imposées n’entraînent pas de frein à l’achat, | P66: 2 les lourdeurs administratives occasionnent des retards de paiement des fournisseurs, | Q66: 1 la communication est suffisante pour les besoins des achats, | T66: 1 - Faible | U66: 2 - Modéré | V66: 1 - Faible | X66: 3 - Important | Y66: 0 - Nul | Z66: 0 - Nul | AC66: 3 - Important | AD66: 1 - Faible | AE66: 2 - Modéré | AG66: 1 - Faible | AH66: 0 - Sécurisé | AI66: Sourcing afin d'assurer un maximum de candidatures lors de la consultation. Optimiser la passation de commandes groupées et le plus tôt possible dans l'année afin de garantir la planification des interventions de maintenance. Participer à des salons prof. | AJ66: 2028 S2 | AK66: Sourcing fournisseurs / benchmark (connaissance offre du marché, connaissance structures de coûts) | AL66: 3.5 | AM66: 3.5 | AN66: 5.6 | AO66: 3.2 | AP66: 0.8 | AQ66: 0 | AR66: Élément | AS66: sites/DNA948/Lists/Analyse de Portefeuille FINA | AT66: =IFERROR(ROUND(IF(Tableau_query__18[[#This Row],[Sous famille]]<>"",VLOOKUP(Tableau_query__18[[#This Row],[Sous famille]],'A013 TCD'!G:H,2,FALSE),VLOOKUP(Tableau_query__18[[#This Row],[Famille d''achat]],'A013 TCD'!D:E,2,FALSE))/1000,0),"") -> 216
A67: 71 | B67: Prestations-Accompagnement psychologique des salariés | C67: 46111 | D67: Services de santé et services sociaux | E67: Prestations | F67: Smahan EL MALAH | H67: 1 les modifications sont minimes et sans conséquence sur l’achat, | I67: 0 égale à la moyenne du secteur, | J67: 1 les précisions nécessaires au fournisseur peuvent être obtenues sans difficulté, | K67: 0 la qualité demandée correspond à la moyenne du marché, | L67: 1 il faut que l’acheteur démontre la pertinence technique des produits de substitution, | M67: 1 les prévisions sont relativement satisfaisantes pour couvrir les besoins des acheteurs, | N67: 0 l’acheteur a toute latitude dans le choix du fournisseur, | O67: 0 il n’y a pas de limite géographique à l’achat, | P67: 0 pas de lourdeur administrative, | Q67: 1 la communication est suffisante pour les besoins des achats, | R67: 0 - Nul | S67: 2 - Modéré | T67: 2 - Modéré | U67: 0 - Nul | V67: 1 - Faible | W67: 0 - Nul | X67: 3 - Important | Y67: 1 - Faible | Z67: 0 - Nul | AA67: 1 - Faible | AC67: 0 - Nul | AD67: 2 - Modéré | AE67: 1 - Faible | AF67: 0 - Nul | AG67: 1 - Faible | AH67: 1 - Très bon niveau | AI67: A renouveler en fonction des besoins RH. Le marché convient bien aux besoins du service RH et aux utilisateurs. Un bilan de marché permettra de revoir les spécifications, voire peut-être d'intégrer des innovations (IA). | AJ67: Renouvellement à prévoir pour avril 2028 | AK67: Optimisation du besoin (bilan du marché avec groupe utilisateurs, meilleure qualité, réduction nombre références, …) | AL67: 2.5 | AM67: 4.5 | AN67: 0 | AO67: 0 | AP67: 1.6 | AQ67: 2.4 | AR67: Élément | AS67: sites/DNA948/Lists/Analyse de Portefeuille FINA | AT67: =IFERROR(ROUND(IF(Tableau_query__18[[#This Row],[Sous famille]]<>"",VLOOKUP(Tableau_query__18[[#This Row],[Sous famille]],'A013 TCD'!G:H,2,FALSE),VLOOKUP(Tableau_query__18[[#This Row],[Famille d''achat]],'A013 TCD'!D:E,2,FALSE))/1000,0),"") -> 189
A68: 72 | B68: Prestations - Services de recrutement | D68: Services de recrutement | E68: Prestations | F68: Smahan EL MALAH | AL68: 0 | AM68: 0 | AN68: 0 | AO68: 0 | AP68: 0 | AQ68: 0 | AR68: Élément | AS68: sites/DNA948/Lists/Analyse de Portefeuille FINA | AT68: =IFERROR(ROUND(IF(Tableau_query__18[[#This Row],[Sous famille]]<>"",VLOOKUP(Tableau_query__18[[#This Row],[Sous famille]],'A013 TCD'!G:H,2,FALSE),VLOOKUP(Tableau_query__18[[#This Row],[Famille d''achat]],'A013 TCD'!D:E,2,FALSE))/1000,0),"") -> 12094
A69: 73 | B69: Prestations - Services de nettoyage et d'hygiène | D69: Services de nettoyage et d'hygiène | E69: Prestations | F69: Stephan DEMONT | AR69: Élément | AS69: sites/DNA948/Lists/Analyse de Portefeuille FINA | AT69: =IFERROR(ROUND(IF(Tableau_query__18[[#This Row],[Sous famille]]<>"",VLOOKUP(Tableau_query__18[[#This Row],[Sous famille]],'A013 TCD'!G:H,2,FALSE),VLOOKUP(Tableau_query__18[[#This Row],[Famille d''achat]],'A013 TCD'!D:E,2,FALSE))/1000,0),"") -> 9207
A70: 74 | B70: Prestations - Services de gardiennage et de surveillance | D70: Services de gardiennage et de surveillance | E70: Prestations | F70: Stéphane DELATOUR | AR70: Élément | AS70: sites/DNA948/Lists/Analyse de Portefeuille FINA | AT70: =IFERROR(ROUND(IF(Tableau_query__18[[#This Row],[Sous famille]]<>"",VLOOKUP(Tableau_query__18[[#This Row],[Sous famille]],'A013 TCD'!G:H,2,FALSE),VLOOKUP(Tableau_query__18[[#This Row],[Famille d''achat]],'A013 TCD'!D:E,2,FALSE))/1000,0),"") -> 3821
A71: 75 | B71: Prestations - Services de certification pour la formation | C71: 45989 | D71: Services de certification pour la formation | E71: Prestations | F71: Ana-Maria REYES-RIPOLL | G71: Frais aux titres de certification + Frais d'agrément pour la formation | H71: 0 elles rejoignent nos propres spécifications, | I71: 0 égale à la moyenne du secteur, | J71: 1 les précisions nécessaires au fournisseur peuvent être obtenues sans difficulté, | L71: 5 aucune marge de manœuvre n’est possible. | M71: 1 les prévisions sont relativement satisfaisantes pour couvrir les besoins des acheteurs, | N71: 4 l’acheteur a des difficultés pour obtenir des conditions commerciales favorables, | O71: 0 il n’y a pas de limite géographique à l’achat, | P71: 0 pas de lourdeur administrative, | Q71: 1 la communication est suffisante pour les besoins des achats, | T71: 0 - Nul | U71: 1 - Faible | V71: 0 - Nul | X71: 1 - Faible | Y71: 1 - Faible | Z71: 0 - Nul | AC71: 0 - Nul | AD71: 0 - Nul | AE71: 2 - Modéré | AG71: 0 - Nul | AH71: 2 - Acceptable | AI71: La catégorie « Frais aux titres de certification » repose principalement sur le pilotage des dispositifs existants plutôt que sur de nouvelles consultations : Les certifications TFP APS en Aquitaine, certification CQPM « Équipier autonome de production industrielle » en Hauts-de-France, certificats, redevances et habilitations CléA, ainsi que la redevance QUALIT’ENR – relèvent de titres propriétaires et de dispositifs encadrés par des organismes ou branches détentrices de droits exclusifs, ce qui ne permet pas une mise en concurrence classique : l’action achat consiste donc à maintenir le recours au gré à gré juridiquement sécurisé (justification par les droits exclusifs et textes de référence), tout en mettant ces dépenses sous contrôle budgétaire via un suivi annuel par type de certification (volumes, coûts unitaires, montants globaux) et l’optimisation des volumes (regroupement de sessions, anticipation des besoins), les leviers d’optimisation portant ainsi sur le pilotage et la sécurisation plutôt que sur la concurrence. La catégorie « Frais d’agrément pour la formation » regroupe les frais d’agrément TFP APS (Nouvelle-Aquitaine, Grand Est, PACA), ainsi que, pour le Siège, les certifications Qualiopi et les redevances annuelles PVE.FIXE, qualiPAC, qualiSOL et qualiPV. Ces dépenses correspondent à des agréments et certifications spécifiques, délivrés par des organismes désignés, pour lesquels il n’existe pas de mise en concurrence possible ; cette catégorie ne nécessite donc pas la mise en place d’un marché formalisé de type MAPA. | AK71: Simplification du processus achat (coût de la commande, ...) | AL71: 0 | AM71: 0 | AN71: 0 | AO71: 0 | AP71: 0 | AQ71: 0 | AR71: Élément | AS71: sites/DNA948/Lists/Analyse de Portefeuille FINA | AT71: =IFERROR(ROUND(IF(Tableau_query__18[[#This Row],[Sous famille]]<>"",VLOOKUP(Tableau_query__18[[#This Row],[Sous famille]],'A013 TCD'!G:H,2,FALSE),VLOOKUP(Tableau_query__18[[#This Row],[Famille d''achat]],'A013 TCD'!D:E,2,FALSE))/1000,0),"")
A72: 76 | B72: Prestations - Services de formations des stagiaires | C72: 46113 | D72: Services de formations des stagiaires | E72: Prestations | F72: Ana-Maria REYES-RIPOLL | H72: 1 les modifications sont minimes et sans conséquence sur l’achat, | I72: 0 égale à la moyenne du secteur, | J72: 2 retarde l’achat en l’absence de responsabilité technique, | K72: 0 la qualité demandée correspond à la moyenne du marché, | L72: 5 aucune marge de manœuvre n’est possible. | M72: 5 les achats ne sont que des achats d’urgence par manque de prévisions. | N72: 1 les impositions correspondent au meilleur choix, | O72: 1 les limites géographiques imposées n’entraînent pas de frein à l’achat, | P72: 2 les lourdeurs administratives occasionnent des retards de paiement des fournisseurs, | Q72: 4 le défaut de communication interne crée un frein à l’étude du marché, | R72: 2 - Modéré | S72: 3 - Important | T72: 1 - Faible | U72: 0 - Nul | V72: 0 - Nul | W72: 1 - Faible | X72: 1 - Faible | Y72: 2 - Modéré | Z72: 0 - Nul | AA72: 1 - Faible | AC72: 0 - Nul | AD72: 1 - Faible | AE72: 0 - Nul | AF72: 1 - Faible | AG72: 0 - Nul | AH72: 4 - Faible | AI72: La sous-famille « Services de formation stagiaire » constitue un segment stratégique du portefeuille, avec 16 K€ de dépenses en 2025, soit un niveau globalement stable par rapport à 2024. Compte tenu de son poids prépondérant, elle justifie une gestion prioritaire afin de sécuriser les achats et d’en améliorer la performance. D’abord, l’évolution des sous-catégories de sous-traitance met en évidence une transformation des pratiques d’achat. Les dépenses de prestations de services de formation confiées aux auto-entrepreneurs et aux entreprises de formation basculent davantage vers la catégorie prestations sous-traitées, avec une hausse de +248 % en paiement direct et de +21,2 % pour les entreprises de formation. Cette évolution traduit les effets positifs du travail mené par la Direction nationale des achats, notamment à travers la formation des acheteurs territoriaux aux consultations simples sur FINA, la normalisation des DCE et la sécurisation des contrats de sous-traitance. Ensuite, l’analyse des dépenses régionales doit être retraitée pour neutraliser certains marchés spécifiques, notamment Parcours Emploi Santé, enregistré principalement dans la catégorie formation sous-traitée par organisme de formation, alors qu’il aurait dû être imputé sur la catégorie service d’aide pédagogique (accompagnement, coaching, ERE). Après correction, les trois principales régions contributrices sont l’Île-de-France (3,3 K€), les Pays de la Loire (1,9 K€) et Auvergne-Rhône-Alpes (1,6 K€). Par ailleurs, la forte progression des régularisations observée en Centre-Val de Loire, Grand Est, Île-de-France, Nouvelle-Aquitaine, PACA et au Siège révèle des difficultés de planification des consultations et de contractualisation en amont. L’analyse met également en évidence des erreurs d’imputation récurrentes portant sur les libellés (règles de nommages non respectés), les sous-familles (prestations de comédiens, Promo 16-18, contrat d’apprentissage…) et les GRN (901, 910…), qui nuisent à la fiabilité de la lecture des dépenses et imposent un retraitement des données sources. Enfin, les délais de validation des notes d’opportunité allongent les calendriers de lancement des consultations MAPA et conduisent certaines régions à recourir à des contrats de sous-traitance avec des dépassements des seuils applicables. Plan d’actions : 1. Renforcer le rappel aux régions sur les règles de nommage, d’imputation et de rattachement aux bonnes sous-familles d’achat et catégories d’achat. 2. Mettre en place une analyse trimestrielle des dépenses par région afin d’identifier les besoins récurrents, d’anticiper les consultations et de sécuriser le recours aux MAPA. 3. Prioriser le lancement des MAPA régionaux dans les régions où la couverture contractuelle est insuffisante, notamment lorsque l’ensemble des contrats issus des précédents MAPA est arrivé à échéance entre 2024 et 2025. Dans ces situations, les régions poursuivent les achats via des contrats de sous-traitance conclus à l’issue des négociations FINA, avec un risque de dépassement des seuils contractuels. 4. Traiter en priorité les régions à plus fort enjeu, en particulier l’Île-de-France, qui représente 20,2 % des dépenses nationales, afin de sécuriser rapidement les achats sur le périmètre le plus exposé. | AJ72: 2026 | AK72: Optimisation de la mise en concurrence (choix procédure, allotissement, critères, pondération) | AL72: 0 | AM72: 0 | AN72: 0 | AO72: 0 | AP72: 0 | AQ72: 0 | AR72: Élément | AS72: sites/DNA948/Lists/Analyse de Portefeuille FINA | AT72: =IFERROR(ROUND(IF(Tableau_query__18[[#This Row],[Sous famille]]<>"",VLOOKUP(Tableau_query__18[[#This Row],[Sous famille]],'A013 TCD'!G:H,2,FALSE),VLOOKUP(Tableau_query__18[[#This Row],[Famille d''achat]],'A013 TCD'!D:E,2,FALSE))/1000,0),"") -> 16210
A73: 77 | B73: Prestations - Services de documentation | C73: 46050 | D73: Services de documentation | E73: Prestations | F73: Cindy CHUNE | G73: IMPRIMES PLAQUETTES ET BROCHURES | H73: 1 les modifications sont minimes et sans conséquence sur l’achat, | I73: 1 de nombreux fournisseurs possèdent le parc requis, | J73: 2 retarde l’achat en l’absence de responsabilité technique, | K73: 0 la qualité demandée correspond à la moyenne du marché, | L73: 0 aucune difficulté pour recourir à des produits de substitution, | M73: 3 les prévisions sont aléatoires, ce qui est préjudiciable aux négociations, | N73: 2 après négociation interne, l’acheteur parvient à qualifier d’autres fournisseurs, | O73: 1 les limites géographiques imposées n’entraînent pas de frein à l’achat, | P73: 1 le circuit administratif retarde les modifications de dossiers d’achat, | Q73: 4 le défaut de communication interne crée un frein à l’étude du marché, | R73: 1 - Faible | S73: 0 - Nul | T73: 1 - Faible | U73: 0 - Nul | V73: 0 - Nul | W73: 1 - Faible | X73: 1 - Faible | Y73: 2 - Modéré | Z73: 2 - Modéré | AA73: 2 - Modéré | AB73: 0 - Nul | AC73: 1 - Faible | AD73: 0 - Nul | AE73: 2 - Modéré | AF73: 2 - Modéré | AG73: 2 - Modéré | AH73: 5 - Critique | AI73: Il s'agit d'impression sur différents supports et formats. Cette famille doit être regroupée avec le de l'impression et signalétique. | AJ73: 2026 | AK73: Harmonisation, standardisation de l'achat | AL73: 5.5 | AM73: 3 | AN73: 3.2 | AO73: 8.8 | AP73: 1.6 | AQ73: 0 | AR73: Élément | AS73: sites/DNA948/Lists/Analyse de Portefeuille FINA | AT73: =IFERROR(ROUND(IF(Tableau_query__18[[#This Row],[Sous famille]]<>"",VLOOKUP(Tableau_query__18[[#This Row],[Sous famille]],'A013 TCD'!G:H,2,FALSE),VLOOKUP(Tableau_query__18[[#This Row],[Famille d''achat]],'A013 TCD'!D:E,2,FALSE))/1000,0),"")
A74: 78 | B74: Prestations - Services de conseil en affaires et en gestion et services connexes. | C74: 46108 | D74: Services de conseil en affaires et en gestion et services connexes. | E74: Prestations | F74: Nathalie CORMIER | H74: 0 elles rejoignent nos propres spécifications, | I74: 1 de nombreux fournisseurs possèdent le parc requis, | J74: 2 retarde l’achat en l’absence de responsabilité technique, | K74: 0 la qualité demandée correspond à la moyenne du marché, | L74: 0 aucune difficulté pour recourir à des produits de substitution, | M74: 5 les achats ne sont que des achats d’urgence par manque de prévisions. | N74: 3 quelques rares fournisseurs imposés peuvent faire l’objet d’une mise en concurrence, | P74: 1 le circuit administratif retarde les modifications de dossiers d’achat, | Q74: 3 la communication ne permet pas d’anticiper les besoins, | R74: 0 - Nul | S74: 0 - Nul | T74: 2 - Modéré | U74: 1 - Faible | V74: 1 - Faible | W74: 0 - Nul | X74: 1 - Faible | Y74: 1 - Faible | Z74: 0 - Nul | AA74: 2 - Modéré | AB74: 1 - Faible | AC74: 1 - Faible | AD74: 2 - Modéré | AE74: 1 - Faible | AF74: 1 - Faible | AG74: 1 - Faible | AH74: 2 - Acceptable | AI74: 87%de couverture contractuelle dont 60% couvert par l'UGAP. Généraliser le recours à l'ugap concernant des prestations de conseil en organisation et gestion générale | AJ74: 2026 | AK74: Faire ou faire faire (externalisation) | AL74: 4 | AM74: 3 | AN74: 1.6 | AO74: 9.6 | AP74: 3.2 | AQ74: 0 | AR74: Élément | AS74: sites/DNA948/Lists/Analyse de Portefeuille FINA | AT74: =IFERROR(ROUND(IF(Tableau_query__18[[#This Row],[Sous famille]]<>"",VLOOKUP(Tableau_query__18[[#This Row],[Sous famille]],'A013 TCD'!G:H,2,FALSE),VLOOKUP(Tableau_query__18[[#This Row],[Famille d''achat]],'A013 TCD'!D:E,2,FALSE))/1000,0),"") -> 359
A75: 79 | B75: Prestations - Services de conception graphique | C75: 46031 | D75: Services de conception graphique | E75: Prestations | F75: Cindy CHUNE | H75: 1 les modifications sont minimes et sans conséquence sur l’achat, | I75: 1 de nombreux fournisseurs possèdent le parc requis, | J75: 2 retarde l’achat en l’absence de responsabilité technique, | K75: 1 la forte concurrence amène les fournisseurs à s’adapter, | L75: 0 aucune difficulté pour recourir à des produits de substitution, | M75: 4 les prévisions n’existent qu’à court terme et ont donc un impact moindre auprès des fournisseurs, | N75: 0 l’acheteur a toute latitude dans le choix du fournisseur, | O75: 1 les limites géographiques imposées n’entraînent pas de frein à l’achat, | P75: 1 le circuit administratif retarde les modifications de dossiers d’achat, | Q75: 1 la communication est suffisante pour les besoins des achats, | R75: 2 - Modéré | S75: 1 - Faible | T75: 2 - Modéré | U75: 2 - Modéré | V75: 0 - Nul | W75: 1 - Faible | X75: 1 - Faible | Y75: 2 - Modéré | Z75: 2 - Modéré | AA75: 1 - Faible | AB75: 2 - Modéré | AC75: 3 - Important | AD75: 2 - Modéré | AE75: 1 - Faible | AF75: 3 - Important | AG75: 0 - Nul | AH75: 5 - Critique | AI75: Mettre en place un marché en 2026 | AJ75: 2026 | AK75: Optimisation de la contractualisation (clauses prix, pénalités, ...) | AL75: 4 | AM75: 3 | AN75: 3.2 | AO75: 6.4 | AP75: 0.8 | AQ75: 0 | AR75: Élément | AS75: sites/DNA948/Lists/Analyse de Portefeuille FINA | AT75: =IFERROR(ROUND(IF(Tableau_query__18[[#This Row],[Sous famille]]<>"",VLOOKUP(Tableau_query__18[[#This Row],[Sous famille]],'A013 TCD'!G:H,2,FALSE),VLOOKUP(Tableau_query__18[[#This Row],[Famille d''achat]],'A013 TCD'!D:E,2,FALSE))/1000,0),"") -> 46
A76: 80 | B76: Prestations - Services d'appui bureautique | C76: 45965 | D76: Services d'appui bureautique | E76: Prestations | F76: Smahan EL MALAH | G76: Rédactionnel et autres appuis administratifs | AI76: dslfkgflxkgn,fdm!ghltklhg:;gbrygjk,h; | AL76: 0 | AM76: 0 | AN76: 0 | AO76: 0 | AP76: 0 | AQ76: 0 | AR76: Élément | AS76: sites/DNA948/Lists/Analyse de Portefeuille FINA | AT76: =IFERROR(ROUND(IF(Tableau_query__18[[#This Row],[Sous famille]]<>"",VLOOKUP(Tableau_query__18[[#This Row],[Sous famille]],'A013 TCD'!G:H,2,FALSE),VLOOKUP(Tableau_query__18[[#This Row],[Famille d''achat]],'A013 TCD'!D:E,2,FALSE))/1000,0),"") -> 60
A77: 81 | B77: Prestations - Services d'analyses bactériologiques | D77: Services d'analyses bactériologiques | E77: Prestations | F77: Laurent AGBOTON | AR77: Élément | AS77: sites/DNA948/Lists/Analyse de Portefeuille FINA | AT77: =IFERROR(ROUND(IF(Tableau_query__18[[#This Row],[Sous famille]]<>"",VLOOKUP(Tableau_query__18[[#This Row],[Sous famille]],'A013 TCD'!G:H,2,FALSE),VLOOKUP(Tableau_query__18[[#This Row],[Famille d''achat]],'A013 TCD'!D:E,2,FALSE))/1000,0),"") -> 42
A78: 82 | B78: Prestations - Service d'organisation d'évènements_SEMINAIRES | C78: 46030 | D78: Service d'organisation d'évènements et de séminaires | E78: Prestations | F78: Cindy CHUNE | G78: Organisation de séminaires | H78: 0 elles rejoignent nos propres spécifications, | I78: 0 égale à la moyenne du secteur, | J78: 1 les précisions nécessaires au fournisseur peuvent être obtenues sans difficulté, | K78: 0 la qualité demandée correspond à la moyenne du marché, | L78: 0 aucune difficulté pour recourir à des produits de substitution, | M78: 1 les prévisions sont relativement satisfaisantes pour couvrir les besoins des acheteurs, | N78: 0 l’acheteur a toute latitude dans le choix du fournisseur, | O78: 0 il n’y a pas de limite géographique à l’achat, | P78: 0 pas de lourdeur administrative, | Q78: 1 la communication est suffisante pour les besoins des achats, | R78: 1 - Faible | S78: 0 - Nul | T78: 1 - Faible | U78: 0 - Nul | V78: 1 - Faible | W78: 0 - Nul | X78: 2 - Modéré | Y78: 1 - Faible | Z78: 2 - Modéré | AA78: 1 - Faible | AB78: 0 - Nul | AC78: 0 - Nul | AD78: 2 - Modéré | AE78: 1 - Faible | AF78: 2 - Modéré | AG78: 1 - Faible | AH78: 4 - Faible | AI78: Cette catégorie Achat " séminaires" dépends surtout des sujets et besoins qui sont ponctuels sur le moment venu. Les dépenses 2025 représente environ 50 000€HT avec 57% du budget utilisés par le National. Le nouveau seuil du MAPA étant fixé 60 000€HT, nous ne mettrons pas en place de marché. | AJ78: NEANT | AK78: Simplification du processus achat (coût de la commande, ...) | AL78: 4.5 | AM78: 3 | AN78: 0.8 | AO78: 0 | AP78: 0 | AQ78: 0 | AR78: Élément | AS78: sites/DNA948/Lists/Analyse de Portefeuille FINA | AT78: =IFERROR(ROUND(IF(Tableau_query__18[[#This Row],[Sous famille]]<>"",VLOOKUP(Tableau_query__18[[#This Row],[Sous famille]],'A013 TCD'!G:H,2,FALSE),VLOOKUP(Tableau_query__18[[#This Row],[Famille d''achat]],'A013 TCD'!D:E,2,FALSE))/1000,0),"") -> 59
A79: 83 | B79: Prestations - Service divertissements, culturels et sportifs | C79: 46091 | D79: Service divertissements, culturels et sportifs | E79: Prestations | F79: Ana-Maria REYES-RIPOLL | H79: 0 elles rejoignent nos propres spécifications, | I79: 0 égale à la moyenne du secteur, | J79: 1 les précisions nécessaires au fournisseur peuvent être obtenues sans difficulté, | L79: 0 aucune difficulté pour recourir à des produits de substitution, | M79: 1 les prévisions sont relativement satisfaisantes pour couvrir les besoins des acheteurs, | N79: 1 les impositions correspondent au meilleur choix, | O79: 0 il n’y a pas de limite géographique à l’achat, | P79: 0 pas de lourdeur administrative, | Q79: 1 la communication est suffisante pour les besoins des achats, | T79: 1 - Faible | U79: 0 - Nul | V79: 0 - Nul | X79: 1 - Faible | Y79: 1 - Faible | Z79: 0 - Nul | AC79: 0 - Nul | AD79: 1 - Faible | AE79: 0 - Nul | AG79: 1 - Faible | AH79: 1 - Très bon niveau | AI79: La sous-famille d’achat « Services divertissements, culturels et sportifs » regroupe principalement les prestations d’animation d’ateliers au bénéfice des publics accueillis dans les dispositifs nationaux d’accompagnement (marché DPN), ainsi que certaines actions liées à la qualité de vie au travail (QVT). Le marché national DPN, renouvelé le 17/12/2024, est en vigueur jusqu’au 16/12/2028. Les marchés du titulaire LEO LAGRANGE ANIMATION ont été résilié le 25/02/2026, et une note d’opportunité est en cours de validation pour renouveler le marché sur les 3 lots HDF, Occitanie et PACA. Il s’agit de renouveler le marché pour 30 mois pour qu’il s’arrête le 16/12/2028. Le renouvellement est déjà prévu du marché national dans les projets. Les autres dépenses de cette sous-famille, de nature plus ponctuelle, contextuelle et souvent de montants plus limités (animations locales, actions QVT spécifiques, événements culturels ou sportifs), sont gérées au niveau local via des consultations adaptées, ce qui permet de tenir compte des besoins de chaque site, de solliciter le tissu d’acteurs locaux et de respecter les règles de mise en concurrence en fonction des seuils applicables, sans nécessité de marché national dédié. | AK79: Optimisation de la mise en concurrence (choix procédure, allotissement, critères, pondération) | AL79: 0 | AM79: 0 | AN79: 0 | AO79: 0 | AP79: 0 | AQ79: 0 | AR79: Élément | AS79: sites/DNA948/Lists/Analyse de Portefeuille FINA | AT79: =IFERROR(ROUND(IF(Tableau_query__18[[#This Row],[Sous famille]]<>"",VLOOKUP(Tableau_query__18[[#This Row],[Sous famille]],'A013 TCD'!G:H,2,FALSE),VLOOKUP(Tableau_query__18[[#This Row],[Famille d''achat]],'A013 TCD'!D:E,2,FALSE))/1000,0),"") -> 535
A80: 84 | B80: Prestations - Service d'ingénierie | D80: Service d'ingénierie | E80: Prestations | F80: Smahan EL MALAH | AR80: Élément | AS80: sites/DNA948/Lists/Analyse de Portefeuille FINA | AT80: =IFERROR(ROUND(IF(Tableau_query__18[[#This Row],[Sous famille]]<>"",VLOOKUP(Tableau_query__18[[#This Row],[Sous famille]],'A013 TCD'!G:H,2,FALSE),VLOOKUP(Tableau_query__18[[#This Row],[Famille d''achat]],'A013 TCD'!D:E,2,FALSE))/1000,0),"") -> 311
A81: 85 | B81: Prestations - Service d'hotellerie et de restauration | C81: 46106 | D81: Service d'hotellerie et de restauration | E81: Prestations | F81: Nathalie CORMIER | G81: Acquisition de titres de restauration | H81: 1 les modifications sont minimes et sans conséquence sur l’achat, | I81: 1 de nombreux fournisseurs possèdent le parc requis, | J81: 2 retarde l’achat en l’absence de responsabilité technique, | K81: 0 la qualité demandée correspond à la moyenne du marché, | L81: 0 aucune difficulté pour recourir à des produits de substitution, | M81: 1 les prévisions sont relativement satisfaisantes pour couvrir les besoins des acheteurs, | N81: 0 l’acheteur a toute latitude dans le choix du fournisseur, | O81: 0 il n’y a pas de limite géographique à l’achat, | P81: 3 le circuit administratif engendre des litiges avec les fournisseurs, | Q81: 3 la communication ne permet pas d’anticiper les besoins, | R81: 2 - Modéré | S81: 1 - Faible | T81: 1 - Faible | U81: 1 - Faible | V81: 1 - Faible | W81: 1 - Faible | X81: 2 - Modéré | Y81: 0 - Nul | Z81: 1 - Faible | AA81: 1 - Faible | AB81: 1 - Faible | AC81: 1 - Faible | AD81: 1 - Faible | AE81: 1 - Faible | AF81: 1 - Faible | AG81: 1 - Faible | AH81: 1 - Très bon niveau | AI81: Remise en concurrence sur la base d'un cahier des charges intégrant l'echange EDI | AJ81: 2027 | AK81: Optimisation du cahier des charges techniques (amélioration des spécifications, cahier des charges fonctionnel) | AL81: 4 | AM81: 4.5 | AN81: 3.2 | AO81: 5.6 | AP81: 4.8 | AQ81: 1.6 | AR81: Élément | AS81: sites/DNA948/Lists/Analyse de Portefeuille FINA | AT81: =IFERROR(ROUND(IF(Tableau_query__18[[#This Row],[Sous famille]]<>"",VLOOKUP(Tableau_query__18[[#This Row],[Sous famille]],'A013 TCD'!G:H,2,FALSE),VLOOKUP(Tableau_query__18[[#This Row],[Famille d''achat]],'A013 TCD'!D:E,2,FALSE))/1000,0),"") -> 1435
A82: 87 | B82: Prestations - Service de réparation et d'entretien d'équipement de restauration | C82: 46106 | D82: Service de réparation et d'entretien d'équipement de restauration | E82: Prestations | F82: Nathalie CORMIER | H82: 1 les modifications sont minimes et sans conséquence sur l’achat, | I82: 1 de nombreux fournisseurs possèdent le parc requis, | J82: 2 retarde l’achat en l’absence de responsabilité technique, | K82: 0 la qualité demandée correspond à la moyenne du marché, | L82: 0 aucune difficulté pour recourir à des produits de substitution, | M82: 1 les prévisions sont relativement satisfaisantes pour couvrir les besoins des acheteurs, | N82: 0 l’acheteur a toute latitude dans le choix du fournisseur, | O82: 1 les limites géographiques imposées n’entraînent pas de frein à l’achat, | P82: 2 les lourdeurs administratives occasionnent des retards de paiement des fournisseurs, | Q82: 2 les contacts sont rares avec les services non directement concernés par l’acte d’achat, | R82: 2 - Modéré | S82: 2 - Modéré | T82: 2 - Modéré | U82: 2 - Modéré | V82: 2 - Modéré | W82: 0 - Nul | X82: 1 - Faible | Y82: 1 - Faible | Z82: 1 - Faible | AA82: 1 - Faible | AB82: 2 - Modéré | AC82: 3 - Important | AD82: 1 - Faible | AE82: 1 - Faible | AF82: 2 - Modéré | AG82: 1 - Faible | AH82: 1 - Très bon niveau | AI82: Aucun plan d'action, compte tenu de la fermeture de nos restaurants au 31/03/2027. Le contrat de maintenance pris en charge par laurent Agboton ne sera maintenu que sur les restaurants pédagogiques | AJ82: 2027 | AK82: Suivi de la performance fournisseurs (tableau de bord, bilan annuel partagé, plan de progrès, …) | AL82: 0 | AM82: 0 | AN82: 3.2 | AO82: 4.8 | AP82: 4 | AQ82: 0.8 | AR82: Élément | AS82: sites/DNA948/Lists/Analyse de Portefeuille FINA | AT82: =IFERROR(ROUND(IF(Tableau_query__18[[#This Row],[Sous famille]]<>"",VLOOKUP(Tableau_query__18[[#This Row],[Sous famille]],'A013 TCD'!G:H,2,FALSE),VLOOKUP(Tableau_query__18[[#This Row],[Famille d''achat]],'A013 TCD'!D:E,2,FALSE))/1000,0),"") -> 743
A83: 88 | B83: Prestations - Service de réparation et d'entretien de moyens de transport | C83: 45958 | D83: Service de réparation et d'entretien de moyens de transport | E83: Prestations | F83: Karine FANTINI | H83: A compléter | I83: A compléter | J83: A Compléter | L83: A compléter | M83: 5 les achats ne sont que des achats d’urgence par manque de prévisions. | N83: 0 l’acheteur a toute latitude dans le choix du fournisseur, | O83: 2 les limites géographiques imposées limitent le choix de fournisseurs, | P83: 0 pas de lourdeur administrative, | Q83: 3 la communication ne permet pas d’anticiper les besoins, | AI83: Achats locaux et en "one shot" effectués par les Acheteurs Territoriaux. Pas de contrat national. | AL83: 0 | AM83: 0 | AN83: 0 | AO83: 0 | AP83: 0 | AQ83: 0 | AR83: Élément | AS83: sites/DNA948/Lists/Analyse de Portefeuille FINA | AT83: =IFERROR(ROUND(IF(Tableau_query__18[[#This Row],[Sous famille]]<>"",VLOOKUP(Tableau_query__18[[#This Row],[Sous famille]],'A013 TCD'!G:H,2,FALSE),VLOOKUP(Tableau_query__18[[#This Row],[Famille d''achat]],'A013 TCD'!D:E,2,FALSE))/1000,0),"") -> 436
A84: 89 | B84: Prestations - Service de réparation et d'entretien de mobilier outillage et petits matériels | D84: Service de réparation et d'entretien de mobilier outillage et petits matériels | E84: Prestations | F84: Stéphane DELATOUR | AR84: Élément | AS84: sites/DNA948/Lists/Analyse de Portefeuille FINA | AT84: =IFERROR(ROUND(IF(Tableau_query__18[[#This Row],[Sous famille]]<>"",VLOOKUP(Tableau_query__18[[#This Row],[Sous famille]],'A013 TCD'!G:H,2,FALSE),VLOOKUP(Tableau_query__18[[#This Row],[Famille d''achat]],'A013 TCD'!D:E,2,FALSE))/1000,0),"")
A85: 90 | B85: Prestations - Service de réparation et d'entretien de matériels de manutention industriels | D85: Service de réparation et d'entretien de matériels de manutention industriels | E85: Prestations | AR85: Élément | AS85: sites/DNA948/Lists/Analyse de Portefeuille FINA | AT85: =IFERROR(ROUND(IF(Tableau_query__18[[#This Row],[Sous famille]]<>"",VLOOKUP(Tableau_query__18[[#This Row],[Sous famille]],'A013 TCD'!G:H,2,FALSE),VLOOKUP(Tableau_query__18[[#This Row],[Famille d''achat]],'A013 TCD'!D:E,2,FALSE))/1000,0),"") -> 251
A86: 91 | B86: Prestations - Service de réparation et d'entretien de matériels de lutte contre l'incendie | D86: Service de réparation et d'entretien de matériels de lutte contre l'incendie | E86: Prestations | AR86: Élément | AS86: sites/DNA948/Lists/Analyse de Portefeuille FINA | AT86: =IFERROR(ROUND(IF(Tableau_query__18[[#This Row],[Sous famille]]<>"",VLOOKUP(Tableau_query__18[[#This Row],[Sous famille]],'A013 TCD'!G:H,2,FALSE),VLOOKUP(Tableau_query__18[[#This Row],[Famille d''achat]],'A013 TCD'!D:E,2,FALSE))/1000,0),"") -> 1134
A87: 92 | B87: Prestations - Service de réparation et d'entretien de matériels de chantier et TP | D87: Service de réparation et d'entretien de matériels de chantier et TP | E87: Prestations | AR87: Élément | AS87: sites/DNA948/Lists/Analyse de Portefeuille FINA | AT87: =IFERROR(ROUND(IF(Tableau_query__18[[#This Row],[Sous famille]]<>"",VLOOKUP(Tableau_query__18[[#This Row],[Sous famille]],'A013 TCD'!G:H,2,FALSE),VLOOKUP(Tableau_query__18[[#This Row],[Famille d''achat]],'A013 TCD'!D:E,2,FALSE))/1000,0),"") -> 557
A88: 93 | B88: Prestations - Service de réparation et d'entretien de chauffage | D88: Service de réparation et d'entretien de chauffage | E88: Prestations | F88: Stéphane DELATOUR | AR88: Élément | AS88: sites/DNA948/Lists/Analyse de Portefeuille FINA | AT88: =IFERROR(ROUND(IF(Tableau_query__18[[#This Row],[Sous famille]]<>"",VLOOKUP(Tableau_query__18[[#This Row],[Sous famille]],'A013 TCD'!G:H,2,FALSE),VLOOKUP(Tableau_query__18[[#This Row],[Famille d''achat]],'A013 TCD'!D:E,2,FALSE))/1000,0),"") -> 3549
A89: 94 | B89: Prestations - Service de publicité et marketing - conseil communication | D89: Service de publicité et marketing | E89: Prestations | F89: Cindy CHUNE | G89: Conseil en communication | H89: 3 les spécifications obligent à des renégociations avec les fournisseurs, | I89: 0 égale à la moyenne du secteur, | J89: 2 retarde l’achat en l’absence de responsabilité technique, | K89: 1 la forte concurrence amène les fournisseurs à s’adapter, | L89: 0 aucune difficulté pour recourir à des produits de substitution, | M89: 1 les prévisions sont relativement satisfaisantes pour couvrir les besoins des acheteurs, | N89: 0 l’acheteur a toute latitude dans le choix du fournisseur, | O89: 0 il n’y a pas de limite géographique à l’achat, | P89: 1 le circuit administratif retarde les modifications de dossiers d’achat, | Q89: 1 la communication est suffisante pour les besoins des achats, | R89: 2 - Modéré | S89: 0 - Nul | T89: 1 - Faible | U89: 1 - Faible | V89: 0 - Nul | W89: 0 - Nul | X89: 1 - Faible | Y89: 1 - Faible | Z89: 2 - Modéré | AA89: 1 - Faible | AC89: 0 - Nul | AD89: 3 - Important | AE89: 3 - Important | AF89: 2 - Modéré | AG89: 2 - Modéré | AH89: 1 - Très bon niveau | AI89: Environ 87% des dépenses du petit enfant sont couverts par des marchés ou abonnement via computacenter. A surveiller | AK89: Suivi de la performance fournisseurs (tableau de bord, bilan annuel partagé, plan de progrès, …) | AL89: 6.5 | AM89: 3 | AN89: 4.8 | AO89: 2.4 | AP89: 1.6 | AQ89: 0 | AR89: Élément | AS89: sites/DNA948/Lists/Analyse de Portefeuille FINA | AT89: =IFERROR(ROUND(IF(Tableau_query__18[[#This Row],[Sous famille]]<>"",VLOOKUP(Tableau_query__18[[#This Row],[Sous famille]],'A013 TCD'!G:H,2,FALSE),VLOOKUP(Tableau_query__18[[#This Row],[Famille d''achat]],'A013 TCD'!D:E,2,FALSE))/1000,0),"") -> 368
A90: 95 | B90: Prestations - Services de formation du Personnel AFPA | D90: Service de gestion du personnel | E90: Prestations | F90: Smahan EL MALAH | G90: Services de formation du Personnel AFPA | AL90: 0 | AM90: 0 | AN90: 0 | AO90: 0 | AP90: 0 | AQ90: 0 | AR90: Élément | AS90: sites/DNA948/Lists/Analyse de Portefeuille FINA | AT90: =IFERROR(ROUND(IF(Tableau_query__18[[#This Row],[Sous famille]]<>"",VLOOKUP(Tableau_query__18[[#This Row],[Sous famille]],'A013 TCD'!G:H,2,FALSE),VLOOKUP(Tableau_query__18[[#This Row],[Famille d''achat]],'A013 TCD'!D:E,2,FALSE))/1000,0),"") -> 1267
A91: 96 | B91: Prestations - Service de gestion du personnel | C91: 46111 | D91: Service de gestion du personnel | E91: Prestations | F91: Smahan EL MALAH | G91: Formation du personnel Afpa | H91: 1 les modifications sont minimes et sans conséquence sur l’achat, | I91: 4 oblige à recourir à plusieurs fournisseurs ou sous-traitants, | J91: 1 les précisions nécessaires au fournisseur peuvent être obtenues sans difficulté, | L91: 1 il faut que l’acheteur démontre la pertinence technique des produits de substitution, | M91: 2 les variations d’activité sont mal évaluées, ce qui oblige à des révisions de contrats, | N91: 2 après négociation interne, l’acheteur parvient à qualifier d’autres fournisseurs, | O91: 0 il n’y a pas de limite géographique à l’achat, | P91: 1 le circuit administratif retarde les modifications de dossiers d’achat, | Q91: 1 la communication est suffisante pour les besoins des achats, | AL91: 0 | AM91: 0 | AN91: 0 | AO91: 0 | AP91: 0 | AQ91: 0 | AR91: Élément | AS91: sites/DNA948/Lists/Analyse de Portefeuille FINA | AT91: =IFERROR(ROUND(IF(Tableau_query__18[[#This Row],[Sous famille]]<>"",VLOOKUP(Tableau_query__18[[#This Row],[Sous famille]],'A013 TCD'!G:H,2,FALSE),VLOOKUP(Tableau_query__18[[#This Row],[Famille d''achat]],'A013 TCD'!D:E,2,FALSE))/1000,0),"")
A92: 97 | B92: Prestations - Service de gestion de blanchisserie et de nettoyage à sec | D92: Service de gestion de blanchisserie et de nettoyage à sec | E92: Prestations | F92: Stéphane DELATOUR | AR92: Élément | AS92: sites/DNA948/Lists/Analyse de Portefeuille FINA | AT92: =IFERROR(ROUND(IF(Tableau_query__18[[#This Row],[Sous famille]]<>"",VLOOKUP(Tableau_query__18[[#This Row],[Sous famille]],'A013 TCD'!G:H,2,FALSE),VLOOKUP(Tableau_query__18[[#This Row],[Famille d''achat]],'A013 TCD'!D:E,2,FALSE))/1000,0),"") -> 193
A93: 98 | B93: Prestations - Service de déménagement - GEPP | C93: 46014 | D93: Service de déménagement | E93: Prestations | F93: Cindy CHUNE | G93: Déménagement des salariés | H93: 0 elles rejoignent nos propres spécifications, | I93: 0 égale à la moyenne du secteur, | J93: 1 les précisions nécessaires au fournisseur peuvent être obtenues sans difficulté, | K93: 0 la qualité demandée correspond à la moyenne du marché, | L93: 0 aucune difficulté pour recourir à des produits de substitution, | M93: 1 les prévisions sont relativement satisfaisantes pour couvrir les besoins des acheteurs, | N93: 0 l’acheteur a toute latitude dans le choix du fournisseur, | O93: 1 les limites géographiques imposées n’entraînent pas de frein à l’achat, | P93: 1 le circuit administratif retarde les modifications de dossiers d’achat, | Q93: 2 les contacts sont rares avec les services non directement concernés par l’acte d’achat, | R93: 1 - Faible | S93: 1 - Faible | T93: 3 - Important | U93: 3 - Important | V93: 1 - Faible | W93: 0 - Nul | X93: 3 - Important | Y93: 3 - Important | Z93: 3 - Important | AA93: 2 - Modéré | AB93: 0 - Nul | AC93: 3 - Important | AD93: 3 - Important | AE93: 3 - Important | AF93: 0 - Nul | AG93: 1 - Faible | AH93: 5 - Critique | AI93: Marché à mettre en place | AJ93: 2026 | AK93: Optimisation de la mise en concurrence (choix procédure, allotissement, critères, pondération) | AL93: 7.5 | AM93: 7.5 | AN93: 0.8 | AO93: 4 | AP93: 0 | AQ93: 0 | AR93: Élément | AS93: sites/DNA948/Lists/Analyse de Portefeuille FINA | AT93: =IFERROR(ROUND(IF(Tableau_query__18[[#This Row],[Sous famille]]<>"",VLOOKUP(Tableau_query__18[[#This Row],[Sous famille]],'A013 TCD'!G:H,2,FALSE),VLOOKUP(Tableau_query__18[[#This Row],[Famille d''achat]],'A013 TCD'!D:E,2,FALSE))/1000,0),"")
A94: 99 | B94: Prestations - Service de conseil juridique, de comptabilité et services fiscaux | C94: 46107 | D94: Service de conseil juridique, de comptabilité et services fiscaux | E94: Prestations | F94: Nathalie CORMIER | H94: 0 elles rejoignent nos propres spécifications, | I94: 1 de nombreux fournisseurs possèdent le parc requis, | J94: 2 retarde l’achat en l’absence de responsabilité technique, | K94: 0 la qualité demandée correspond à la moyenne du marché, | L94: 0 aucune difficulté pour recourir à des produits de substitution, | M94: 3 les prévisions sont aléatoires, ce qui est préjudiciable aux négociations, | N94: 3 quelques rares fournisseurs imposés peuvent faire l’objet d’une mise en concurrence, | O94: 1 les limites géographiques imposées n’entraînent pas de frein à l’achat, | P94: 1 le circuit administratif retarde les modifications de dossiers d’achat, | Q94: 3 la communication ne permet pas d’anticiper les besoins, | R94: 2 - Modéré | S94: 1 - Faible | T94: 1 - Faible | U94: 1 - Faible | V94: 1 - Faible | W94: 1 - Faible | X94: 1 - Faible | Y94: 1 - Faible | Z94: 0 - Nul | AA94: 1 - Faible | AC94: 1 - Faible | AD94: 1 - Faible | AE94: 1 - Faible | AF94: 1 - Faible | AG94: 1 - Faible | AH94: 2 - Acceptable | AI94: Le taux de couverture contractuelle selon les 3 catégories d'achats, audits comptable et financier, conseil juridique et service de comptabilité sont entre 63% et 97%. Cette couverture est acceptable, sachant que dans le conseil juridique il y a parfois des mauvaises affectations (ex huissiers qui ne sont pas soumis au CCP ainsi que les prestations de représentations légales. Pas vraiment de plan d'action excepté peut-être de voir s'il existe des contrats à l'UGAP pour remplacer nos contrats existants | AJ94: 2029 | AK94: Faire ou faire faire (externalisation) | AL94: 3 | AM94: 4.5 | AN94: 2.4 | AO94: 8.8 | AP94: 2.4 | AQ94: 0 | AR94: Élément | AS94: sites/DNA948/Lists/Analyse de Portefeuille FINA | AT94: =IFERROR(ROUND(IF(Tableau_query__18[[#This Row],[Sous famille]]<>"",VLOOKUP(Tableau_query__18[[#This Row],[Sous famille]],'A013 TCD'!G:H,2,FALSE),VLOOKUP(Tableau_query__18[[#This Row],[Famille d''achat]],'A013 TCD'!D:E,2,FALSE))/1000,0),"") -> 1567
A95: 100 | B95: Prestations - Service de conseil en ressources humaines | D95: Service de conseil en ressources humaines | E95: Prestations | F95: Smahan EL MALAH | AR95: Élément | AS95: sites/DNA948/Lists/Analyse de Portefeuille FINA | AT95: =IFERROR(ROUND(IF(Tableau_query__18[[#This Row],[Sous famille]]<>"",VLOOKUP(Tableau_query__18[[#This Row],[Sous famille]],'A013 TCD'!G:H,2,FALSE),VLOOKUP(Tableau_query__18[[#This Row],[Famille d''achat]],'A013 TCD'!D:E,2,FALSE))/1000,0),"") -> 47
A96: 101 | B96: Prestations - Service d'archivage | C96: 46014 | D96: Service d'archivage | E96: Prestations | F96: Cindy CHUNE | H96: 1 les modifications sont minimes et sans conséquence sur l’achat, | I96: 1 de nombreux fournisseurs possèdent le parc requis, | J96: 1 les précisions nécessaires au fournisseur peuvent être obtenues sans difficulté, | K96: 0 la qualité demandée correspond à la moyenne du marché, | L96: 1 il faut que l’acheteur démontre la pertinence technique des produits de substitution, | M96: 1 les prévisions sont relativement satisfaisantes pour couvrir les besoins des acheteurs, | N96: 1 les impositions correspondent au meilleur choix, | O96: 1 les limites géographiques imposées n’entraînent pas de frein à l’achat, | P96: 0 pas de lourdeur administrative, | Q96: 1 la communication est suffisante pour les besoins des achats, | R96: 1 - Faible | S96: 3 - Important | T96: 1 - Faible | U96: 0 - Nul | V96: 0 - Nul | W96: 0 - Nul | X96: 0 - Nul | Y96: 1 - Faible | Z96: 3 - Important | AA96: 3 - Important | AB96: 0 - Nul | AC96: 0 - Nul | AD96: 3 - Important | AE96: 3 - Important | AF96: 0 - Nul | AG96: 0 - Nul | AH96: 1 - Très bon niveau | AI96: Préparer le renouvellement du marché (actualiser le besoin,...) | AJ96: 2027 | AK96: Optimisation du besoin (bilan du marché avec groupe utilisateurs, meilleure qualité, réduction nombre références, …) | AL96: 6 | AM96: 3 | AN96: 0 | AO96: 0 | AP96: 0 | AQ96: 0 | AR96: Élément | AS96: sites/DNA948/Lists/Analyse de Portefeuille FINA | AT96: =IFERROR(ROUND(IF(Tableau_query__18[[#This Row],[Sous famille]]<>"",VLOOKUP(Tableau_query__18[[#This Row],[Sous famille]],'A013 TCD'!G:H,2,FALSE),VLOOKUP(Tableau_query__18[[#This Row],[Famille d''achat]],'A013 TCD'!D:E,2,FALSE))/1000,0),"") -> 220
A97: 102 | B97: Prestations - Centre d'appel | C97: 46106 | D97: Centre d'appel | E97: Prestations | F97: Nathalie CORMIER | G97: Accueil téléphonique | H97: 1 les modifications sont minimes et sans conséquence sur l’achat, | I97: 1 de nombreux fournisseurs possèdent le parc requis, | J97: 4 occasionne des achats approximatifs, | K97: 0 la qualité demandée correspond à la moyenne du marché, | L97: 2 produits imposés pour certaines phases de production, | M97: 2 les variations d’activité sont mal évaluées, ce qui oblige à des révisions de contrats, | N97: 0 l’acheteur a toute latitude dans le choix du fournisseur, | O97: 2 les limites géographiques imposées limitent le choix de fournisseurs, | P97: 1 le circuit administratif retarde les modifications de dossiers d’achat, | Q97: 1 la communication est suffisante pour les besoins des achats, | R97: 2 - Modéré | S97: 1 - Faible | T97: 2 - Modéré | U97: 1 - Faible | V97: 4 - Majeur | W97: 1 - Faible | X97: 2 - Modéré | Y97: 2 - Modéré | Z97: 0 - Nul | AA97: 2 - Modéré | AB97: 3 - Important | AC97: 0 - Nul | AD97: 2 - Modéré | AE97: 1 - Faible | AF97: 1 - Faible | AG97: 2 - Modéré | AH97: 1 - Très bon niveau | AI97: La PAN a démontré son efficacité lors des 2 dernières mises en concurrence. Ce levier de mise en concurrence est actionnable à chaque renouvellement. Le mécanisme bonus/malus indexé sur des KPI à forte valeur ajoutée (taux de transformation d'appel, taux de satisfaction, taux de décroché) constitue un levier de pilotage de la performance en continu. Ce modèle doit être affiné dès le démarrage pour éviter les zones grises. Un autre levier celui de IA et de l'omnicanalité est important et structurant permettant d'optimiser les parcours et réduire la DMT; Autre levier, celui de la réduction des volumes d'appels et donc des coûts avec la digitalisation progressive. 2 facteurs : le nouveau site web afpa (horizon 2026) va permettre la bascule vers le canal digital. Orchestrateur de flux (horizon 2027) : économies estimées à -30% sur le budget (source Bearing Point). La clause de revoyure prévue va permettre de réviser les volumes réels, d'ajuster les prix unitaires en lien avec les gains d'efficacité et d'intégrer les KPIs opérationnels (taux de bascule web, coût par contact résiduel). C'est un levier de sécurisation budgétaire essentiel dans un contexte de transformation numérique. Plan d'action : juillet 2026 -juin 2027: optimisation et revoyure - Innovation et préparation renouvellement (2028-2029) : Evaluation des conditions de reconduction (36ème mois)- Veille marché - Bilan performance achats global. Lancement NO N+1 si non reconduction. | AJ97: 2027 | AK97: Suivi de la performance fournisseurs (tableau de bord, bilan annuel partagé, plan de progrès, …) | AL97: 4 | AM97: 5.5 | AN97: 6.4 | AO97: 4.8 | AP97: 4.8 | AQ97: 3.2 | AR97: Élément | AS97: sites/DNA948/Lists/Analyse de Portefeuille FINA | AT97: =IFERROR(ROUND(IF(Tableau_query__18[[#This Row],[Sous famille]]<>"",VLOOKUP(Tableau_query__18[[#This Row],[Sous famille]],'A013 TCD'!G:H,2,FALSE),VLOOKUP(Tableau_query__18[[#This Row],[Famille d''achat]],'A013 TCD'!D:E,2,FALSE))/1000,0),"") -> 1850
A98: 103 | B98: Prestations - Service 3D - dératisation desinsectisation desinfection | D98: Service 3D - dératisation desinsectisation desinfection | E98: Prestations | F98: Stéphane DELATOUR | AR98: Élément | AS98: sites/DNA948/Lists/Analyse de Portefeuille FINA | AT98: =IFERROR(ROUND(IF(Tableau_query__18[[#This Row],[Sous famille]]<>"",VLOOKUP(Tableau_query__18[[#This Row],[Sous famille]],'A013 TCD'!G:H,2,FALSE),VLOOKUP(Tableau_query__18[[#This Row],[Famille d''achat]],'A013 TCD'!D:E,2,FALSE))/1000,0),"") -> 360
A99: 104 | B99: Prestations - Multi techniques et multiservices | C99: 45959 | D99: Multi techniques et multiservices | E99: Prestations | F99: Karine FANTINI | H99: 1 les modifications sont minimes et sans conséquence sur l’achat, | I99: 0 égale à la moyenne du secteur, | J99: 2 retarde l’achat en l’absence de responsabilité technique, | L99: 0 aucune difficulté pour recourir à des produits de substitution, | M99: 3 les prévisions sont aléatoires, ce qui est préjudiciable aux négociations, | N99: 0 l’acheteur a toute latitude dans le choix du fournisseur, | O99: 2 les limites géographiques imposées limitent le choix de fournisseurs, | P99: 2 les lourdeurs administratives occasionnent des retards de paiement des fournisseurs, | Q99: 3 la communication ne permet pas d’anticiper les besoins, | T99: 2 - Modéré | U99: 4 - Majeur | V99: 2 - Modéré | X99: 2 - Modéré | Y99: 2 - Modéré | Z99: 1 - Faible | AC99: 0 - Nul | AD99: 2 - Modéré | AE99: 2 - Modéré | AG99: 1 - Faible | AH99: 1 - Très bon niveau | AI99: Allotissement local (Centre/Territoire) et publication par les régions afin de favoriser les candidats micro-entreprises avec une meilleure adaptation aux besoins des Centres et une optimisation du coût horaire. Pilotage national des consultations avec mise à disposition d'un DCE type. | AJ99: 2025 S2 | AK99: Optimisation de la mise en concurrence (choix procédure, allotissement, critères, pondération) | AL99: 3 | AM99: 6 | AN99: 2.4 | AO99: 8 | AP99: 1.6 | AQ99: 0.8 | AR99: Élément | AS99: sites/DNA948/Lists/Analyse de Portefeuille FINA | AT99: =IFERROR(ROUND(IF(Tableau_query__18[[#This Row],[Sous famille]]<>"",VLOOKUP(Tableau_query__18[[#This Row],[Sous famille]],'A013 TCD'!G:H,2,FALSE),VLOOKUP(Tableau_query__18[[#This Row],[Famille d''achat]],'A013 TCD'!D:E,2,FALSE))/1000,0),"") -> 3885
A100: 105 | B100: Prestations - Maintenance et réparation | D100: Maintenance et réparation | E100: Prestations | AR100: Élément | AS100: sites/DNA948/Lists/Analyse de Portefeuille FINA | AT100: =IFERROR(ROUND(IF(Tableau_query__18[[#This Row],[Sous famille]]<>"",VLOOKUP(Tableau_query__18[[#This Row],[Sous famille]],'A013 TCD'!G:H,2,FALSE),VLOOKUP(Tableau_query__18[[#This Row],[Famille d''achat]],'A013 TCD'!D:E,2,FALSE))/1000,0),"") -> 309
A101: 106 | B101: Prestations - Etudes de marché et recherches économiques ; sondages et statistiques. | C101: 46106 | D101: Etudes de marché et recherches économiques ; sondages et statistiques. | E101: Prestations | F101: Nathalie CORMIER | H101: 0 elles rejoignent nos propres spécifications, | I101: 0 égale à la moyenne du secteur, | J101: 1 les précisions nécessaires au fournisseur peuvent être obtenues sans difficulté, | K101: 0 la qualité demandée correspond à la moyenne du marché, | L101: 2 produits imposés pour certaines phases de production, | M101: 2 les variations d’activité sont mal évaluées, ce qui oblige à des révisions de contrats, | N101: 1 les impositions correspondent au meilleur choix, | O101: 1 les limites géographiques imposées n’entraînent pas de frein à l’achat, | P101: 0 pas de lourdeur administrative, | Q101: 1 la communication est suffisante pour les besoins des achats, | R101: 3 - Important | S101: 1 - Faible | T101: 1 - Faible | U101: 1 - Faible | V101: 1 - Faible | W101: 1 - Faible | X101: 1 - Faible | Y101: 1 - Faible | Z101: 1 - Faible | AA101: 1 - Faible | AC101: 1 - Faible | AD101: 1 - Faible | AE101: 1 - Faible | AF101: 2 - Modéré | AG101: 1 - Faible | AH101: 1 - Très bon niveau | AI101: 1-Sourcing marché fournisseurs — préparation 2028 Identifier les acteurs capables de répondre à un futur DCE : IPSOS, KANTAR, BVA Group, Ifop, Opinion Way, et nouveaux entrants tech (collecte CAWI augmentée, IA de scoring) Organiser 2 à 3 RDV sourcing avant toute procédure Utiliser le BOAMP (sourcing public)? BRAPI et MAIA pour benchmark TJM prestations intellectuelles 2-Note d'opportunité et DCE 2028 — marché LVDC (98% du CA de la famille ; Lancer la procédure 18 mois avant la fin du marché (fin contrat actuel : ~juillet 2028) Intégrer les retours d'expérience du marché 2024-2028 : performance achat réelle vs -3% estimé, qualité des livrables, incidents RGPD Viser un BPU renforcé avec paliers de volume dégressifs Livrable : note d'opportunité validée en commission achats T1 2028, publication DCE T2 2028 3-Intégrer une clause sociale dans le prochain DCE Identifier une clause d'insertion réaliste pour un marché de télé-enquête | AJ101: 2028 | AK101: Achat Innovant (veille technique - maîtrise marché fournisseurs) | AL101: 4 | AM101: 5 | AN101: 2.4 | AO101: 4 | AP101: 5.6 | AQ101: 0 | AR101: Élément | AS101: sites/DNA948/Lists/Analyse de Portefeuille FINA | AT101: =IFERROR(ROUND(IF(Tableau_query__18[[#This Row],[Sous famille]]<>"",VLOOKUP(Tableau_query__18[[#This Row],[Sous famille]],'A013 TCD'!G:H,2,FALSE),VLOOKUP(Tableau_query__18[[#This Row],[Famille d''achat]],'A013 TCD'!D:E,2,FALSE))/1000,0),"") -> 1459
A102: 107 | B102: Prestations - Entretien des espaces verts | D102: Entretien des espaces verts | E102: Prestations | F102: Stéphane DELATOUR | AR102: Élément | AS102: sites/DNA948/Lists/Analyse de Portefeuille FINA | AT102: =IFERROR(ROUND(IF(Tableau_query__18[[#This Row],[Sous famille]]<>"",VLOOKUP(Tableau_query__18[[#This Row],[Sous famille]],'A013 TCD'!G:H,2,FALSE),VLOOKUP(Tableau_query__18[[#This Row],[Famille d''achat]],'A013 TCD'!D:E,2,FALSE))/1000,0),"") -> 1863
A103: 108 | B103: Prestations - Energies et fluides | D103: Energies et fluides | E103: Prestations | F103: Stéphane DELATOUR | AR103: Élément | AS103: sites/DNA948/Lists/Analyse de Portefeuille FINA | AT103: =IFERROR(ROUND(IF(Tableau_query__18[[#This Row],[Sous famille]]<>"",VLOOKUP(Tableau_query__18[[#This Row],[Sous famille]],'A013 TCD'!G:H,2,FALSE),VLOOKUP(Tableau_query__18[[#This Row],[Famille d''achat]],'A013 TCD'!D:E,2,FALSE))/1000,0),"") -> 22739
A104: 109 | B104: Prestations - Droits d'auteurs et prestations diverses | C104: 46014 | D104: Droits d'auteurs et prestations diverses | E104: Prestations | F104: Cindy CHUNE | H104: 0 elles rejoignent nos propres spécifications, | I104: 0 égale à la moyenne du secteur, | J104: 0 sans impact pour l’achat, | K104: 0 la qualité demandée correspond à la moyenne du marché, | L104: 0 aucune difficulté pour recourir à des produits de substitution, | M104: 0 les prévisions à moyen et long terme sont fiables, | N104: 0 l’acheteur a toute latitude dans le choix du fournisseur, | O104: 0 il n’y a pas de limite géographique à l’achat, | P104: 0 pas de lourdeur administrative, | Q104: 0 la communication interne est excellente et fiable, | R104: 4 - Majeur | S104: 0 - Nul | T104: 0 - Nul | U104: 0 - Nul | V104: 1 - Faible | W104: 0 - Nul | X104: 0 - Nul | Y104: 0 - Nul | Z104: 0 - Nul | AA104: 0 - Nul | AB104: 0 - Nul | AC104: 0 - Nul | AD104: 0 - Nul | AE104: 0 - Nul | AF104: 0 - Nul | AG104: 0 - Nul | AH104: 0 - Sécurisé | AI104: Les droits d'auteur constituent un élément contractuel intégré aux marchés de prestations intellectuelles ou créatives. Il n'est donc pas possible de mettre en place exclusivement un marché pour les droits d'auteurs. Les coûts sont imposés et calculés par une institution spécifique. | AJ104: pas de programmation | AL104: 0 | AM104: 0.5 | AN104: 0 | AO104: 0 | AP104: 1.6 | AQ104: 0.8 | AR104: Élément | AS104: sites/DNA948/Lists/Analyse de Portefeuille FINA | AT104: =IFERROR(ROUND(IF(Tableau_query__18[[#This Row],[Sous famille]]<>"",VLOOKUP(Tableau_query__18[[#This Row],[Sous famille]],'A013 TCD'!G:H,2,FALSE),VLOOKUP(Tableau_query__18[[#This Row],[Famille d''achat]],'A013 TCD'!D:E,2,FALSE))/1000,0),"") -> 85
A105: 110 | B105: Prestations - Courrier et affranchissements | D105: Courrier et affranchissements | E105: Prestations | F105: Smahan EL MALAH | AR105: Élément | AS105: sites/DNA948/Lists/Analyse de Portefeuille FINA | AT105: =IFERROR(ROUND(IF(Tableau_query__18[[#This Row],[Sous famille]]<>"",VLOOKUP(Tableau_query__18[[#This Row],[Sous famille]],'A013 TCD'!G:H,2,FALSE),VLOOKUP(Tableau_query__18[[#This Row],[Famille d''achat]],'A013 TCD'!D:E,2,FALSE))/1000,0),"") -> 2308
A106: 111 | B106: Prestations - Contrôle technique | D106: Contrôle technique | E106: Prestations | F106: Karine FANTINI | H106: 0 elles rejoignent nos propres spécifications, | I106: 1 de nombreux fournisseurs possèdent le parc requis, | J106: 0 sans impact pour l’achat, | L106: 0 aucune difficulté pour recourir à des produits de substitution, | M106: 0 les prévisions à moyen et long terme sont fiables, | N106: 0 l’acheteur a toute latitude dans le choix du fournisseur, | O106: 1 les limites géographiques imposées n’entraînent pas de frein à l’achat, | P106: 0 pas de lourdeur administrative, | Q106: 0 la communication interne est excellente et fiable, | T106: 0 - Nul | U106: 0 - Nul | V106: 0 - Nul | X106: 0 - Nul | Y106: 0 - Nul | Z106: 1 - Faible | AC106: 0 - Nul | AD106: 1 - Faible | AE106: 0 - Nul | AG106: 0 - Nul | AH106: 2 - Acceptable | AI106: Achat local effectué par les Acheteurs Territoriaux pour les véhicules en propriété. Prestation incluse au marché LLD de la flotte de véhicule service. | AL106: 1 | AM106: 0 | AN106: 0 | AO106: 0 | AP106: 0 | AQ106: 0 | AR106: Élément | AS106: sites/DNA948/Lists/Analyse de Portefeuille FINA | AT106: =IFERROR(ROUND(IF(Tableau_query__18[[#This Row],[Sous famille]]<>"",VLOOKUP(Tableau_query__18[[#This Row],[Sous famille]],'A013 TCD'!G:H,2,FALSE),VLOOKUP(Tableau_query__18[[#This Row],[Famille d''achat]],'A013 TCD'!D:E,2,FALSE))/1000,0),"") -> 16
A107: 112 | B107: Prestations - Contrôle reglementaire | C107: 45959 | D107: Contrôle reglementaire | E107: Prestations | F107: Karine FANTINI | H107: 0 elles rejoignent nos propres spécifications, | I107: 1 de nombreux fournisseurs possèdent le parc requis, | J107: 1 les précisions nécessaires au fournisseur peuvent être obtenues sans difficulté, | L107: 5 aucune marge de manœuvre n’est possible. | M107: 0 les prévisions à moyen et long terme sont fiables, | N107: 0 l’acheteur a toute latitude dans le choix du fournisseur, | O107: 1 les limites géographiques imposées n’entraînent pas de frein à l’achat, | P107: 2 les lourdeurs administratives occasionnent des retards de paiement des fournisseurs, | Q107: 1 la communication est suffisante pour les besoins des achats, | T107: 2 - Modéré | U107: 3 - Important | V107: 1 - Faible | X107: 3 - Important | Y107: 1 - Faible | Z107: 2 - Modéré | AC107: 3 - Important | AD107: 3 - Important | AE107: 2 - Modéré | AG107: 1 - Faible | AH107: 0 - Sécurisé | AI107: L'allotissement actuel (géographique) n'étant pas pertinent, car les acteurs du marché ont une couverture nationale. Regroupement des marchés contrôles des équipements et contrôles des installations sur une consultation unique avec des lots techniques : 1 pour chacun des 2 items cités. | AJ107: 2025 S2 | AK107: Optimisation de la mise en concurrence (choix procédure, allotissement, critères, pondération) | AL107: 5.5 | AM107: 0 | AN107: 0 | AO107: 0 | AP107: 0 | AQ107: 0 | AR107: Élément | AS107: sites/DNA948/Lists/Analyse de Portefeuille FINA | AT107: =IFERROR(ROUND(IF(Tableau_query__18[[#This Row],[Sous famille]]<>"",VLOOKUP(Tableau_query__18[[#This Row],[Sous famille]],'A013 TCD'!G:H,2,FALSE),VLOOKUP(Tableau_query__18[[#This Row],[Famille d''achat]],'A013 TCD'!D:E,2,FALSE))/1000,0),"") -> 1092
A108: 114 | B108: Prestations - Annonces et insertions | C108: 46001 | D108: Annonces et insertions | E108: Prestations | F108: Cindy CHUNE | H108: 0 elles rejoignent nos propres spécifications, | I108: 0 égale à la moyenne du secteur, | J108: 0 sans impact pour l’achat, | K108: 0 la qualité demandée correspond à la moyenne du marché, | L108: 1 il faut que l’acheteur démontre la pertinence technique des produits de substitution, | M108: 1 les prévisions sont relativement satisfaisantes pour couvrir les besoins des acheteurs, | N108: 1 les impositions correspondent au meilleur choix, | O108: 0 il n’y a pas de limite géographique à l’achat, | P108: 0 pas de lourdeur administrative, | Q108: 1 la communication est suffisante pour les besoins des achats, | R108: 4 - Majeur | S108: 0 - Nul | T108: 0 - Nul | U108: 0 - Nul | V108: 0 - Nul | W108: 3 - Important | X108: 0 - Nul | Y108: 1 - Faible | Z108: 0 - Nul | AA108: 1 - Faible | AB108: 2 - Modéré | AC108: 0 - Nul | AD108: 2 - Modéré | AE108: 0 - Nul | AF108: 3 - Important | AG108: 0 - Nul | AH108: 0 - Sécurisé | AI108: 90% des achats sont réalisés avec des fournisseurs ayant leur spécificité (monopole). Sur les 10% restant une surveillance des dépenses sera mise ne place dans le 1er semestre 2026 | AJ108: non prioritaire | AK108: Suivi de la performance fournisseurs (tableau de bord, bilan annuel partagé, plan de progrès, …) | AL108: 1 | AM108: 0.5 | AN108: 0 | AO108: 0 | AP108: 0 | AQ108: 0 | AR108: Élément | AS108: sites/DNA948/Lists/Analyse de Portefeuille FINA | AT108: =IFERROR(ROUND(IF(Tableau_query__18[[#This Row],[Sous famille]]<>"",VLOOKUP(Tableau_query__18[[#This Row],[Sous famille]],'A013 TCD'!G:H,2,FALSE),VLOOKUP(Tableau_query__18[[#This Row],[Famille d''achat]],'A013 TCD'!D:E,2,FALSE))/1000,0),"") -> 1081
A109: 115 | B109: Prestations - Services de cotisation à associations et clubs professionnels | C109: 45987 | D109: Services de cotisation à associations et clubs professionnels | E109: Prestations | F109: Cindy CHUNE | H109: 0 elles rejoignent nos propres spécifications, | I109: 0 égale à la moyenne du secteur, | J109: 0 sans impact pour l’achat, | K109: 0 la qualité demandée correspond à la moyenne du marché, | L109: 0 aucune difficulté pour recourir à des produits de substitution, | M109: 1 les prévisions sont relativement satisfaisantes pour couvrir les besoins des acheteurs, | N109: 0 l’acheteur a toute latitude dans le choix du fournisseur, | O109: 2 les limites géographiques imposées limitent le choix de fournisseurs, | P109: 0 pas de lourdeur administrative, | Q109: 1 la communication est suffisante pour les besoins des achats, | R109: 1 - Faible | S109: 0 - Nul | T109: 0 - Nul | U109: 0 - Nul | V109: 0 - Nul | W109: 0 - Nul | X109: 0 - Nul | Y109: 1 - Faible | Z109: 0 - Nul | AA109: 0 - Nul | AB109: 0 - Nul | AC109: 0 - Nul | AD109: 0 - Nul | AE109: 1 - Faible | AF109: 1 - Faible | AG109: 2 - Modéré | AH109: 0 - Sécurisé | AI109: Le segment d'achat relatif aux Services de cotisation à associations et clubs professionnels relève plutôt des dispositifs de partenariats dont les engagements se concrétise via les conventions . En effet, ces prestations sont régies par des conventions bilatérales signées selon les besoins spécifiques, plutôt que par des marchés publics formalisés. Cette modalité contractuelle répond à la nature des besoins, de caractère local et régional, pris en charge en toute autonomie par chaque centre Afpa en fonction de ses priorités institutionnelles. En conséquence, aucune procédure de marché n'est requise. | AK109: Autre levier (à préciser) | AL109: 1.5 | AM109: 0.5 | AN109: 0 | AO109: 3.2 | AP109: 0 | AQ109: 0.8 | AR109: Élément | AS109: sites/DNA948/Lists/Analyse de Portefeuille FINA | AT109: =IFERROR(ROUND(IF(Tableau_query__18[[#This Row],[Sous famille]]<>"",VLOOKUP(Tableau_query__18[[#This Row],[Sous famille]],'A013 TCD'!G:H,2,FALSE),VLOOKUP(Tableau_query__18[[#This Row],[Famille d''achat]],'A013 TCD'!D:E,2,FALSE))/1000,0),"") -> 198
A110: 116 | B110: Services de certification pour la formation | C110: 46113 | D110: Services de certification ou d'agrément pour la formation | E110: Prestations | F110: Ana-Maria REYES-RIPOLL | G110: Services de comédiens | H110: 0 elles rejoignent nos propres spécifications, | I110: 0 égale à la moyenne du secteur, | J110: 0 sans impact pour l’achat, | L110: 0 aucune difficulté pour recourir à des produits de substitution, | M110: 4 les prévisions n’existent qu’à court terme et ont donc un impact moindre auprès des fournisseurs, | N110: 0 l’acheteur a toute latitude dans le choix du fournisseur, | O110: 1 les limites géographiques imposées n’entraînent pas de frein à l’achat, | P110: 0 pas de lourdeur administrative, | Q110: 1 la communication est suffisante pour les besoins des achats, | T110: 0 - Nul | U110: 0 - Nul | V110: 0 - Nul | X110: 0 - Nul | Y110: 1 - Faible | Z110: 0 - Nul | AC110: 1 - Faible | AD110: 0 - Nul | AE110: 0 - Nul | AG110: 0 - Nul | AH110: 4 - Faible | AI110: La catégorie d’achat « services de comédiens » ne fera pas l’objet d’un MAPA national, la dépense annuelle étant inférieure à 40 k€ et le marché étant constitué essentiellement de prestataires locaux qui ne répondent pas à des procédures formalisées complexes au niveau national ; cette catégorie sera donc gérée au niveau régional, via des consultations adaptées auprès de comédiens locaux, dans le respect des seuils et règles de la commande publique. | AK110: Optimisation de la mise en concurrence (choix procédure, allotissement, critères, pondération) | AL110: 0 | AM110: 0 | AN110: 0 | AO110: 0 | AP110: 0 | AQ110: 0 | AR110: Élément | AS110: sites/DNA948/Lists/Analyse de Portefeuille FINA | AT110: =IFERROR(ROUND(IF(Tableau_query__18[[#This Row],[Sous famille]]<>"",VLOOKUP(Tableau_query__18[[#This Row],[Sous famille]],'A013 TCD'!G:H,2,FALSE),VLOOKUP(Tableau_query__18[[#This Row],[Famille d''achat]],'A013 TCD'!D:E,2,FALSE))/1000,0),"") -> 194
A111: 118 | B111: Prestations - Audits et certifications | D111: Audits et certifications | E111: Prestations | F111: Stéphane DELATOUR | AR111: Élément | AS111: sites/DNA948/Lists/Analyse de Portefeuille FINA | AT111: =IFERROR(ROUND(IF(Tableau_query__18[[#This Row],[Sous famille]]<>"",VLOOKUP(Tableau_query__18[[#This Row],[Sous famille]],'A013 TCD'!G:H,2,FALSE),VLOOKUP(Tableau_query__18[[#This Row],[Famille d''achat]],'A013 TCD'!D:E,2,FALSE))/1000,0),"") -> 282
A112: 119 | B112: Travaux - Terrains et immeubles | C112: 46112 | D112: Terrains et immeubles | E112: Travaux | F112: Paola ANTONELLI | G112: Location salles courte durée sans bail | H112: 0 elles rejoignent nos propres spécifications, | I112: 0 égale à la moyenne du secteur, | J112: 0 sans impact pour l’achat, | K112: 0 la qualité demandée correspond à la moyenne du marché, | L112: 0 aucune difficulté pour recourir à des produits de substitution, | M112: 1 les prévisions sont relativement satisfaisantes pour couvrir les besoins des acheteurs, | N112: 0 l’acheteur a toute latitude dans le choix du fournisseur, | O112: 0 il n’y a pas de limite géographique à l’achat, | P112: 0 pas de lourdeur administrative, | Q112: 3 la communication ne permet pas d’anticiper les besoins, | R112: 2 - Modéré | S112: 2 - Modéré | T112: 1 - Faible | U112: 2 - Modéré | V112: 1 - Faible | W112: 0 - Nul | X112: 2 - Modéré | Y112: 1 - Faible | Z112: 0 - Nul | AA112: 0 - Nul | AB112: 0 - Nul | AC112: 0 - Nul | AD112: 1 - Faible | AE112: 1 - Faible | AF112: 0 - Nul | AG112: 0 - Nul | AH112: 5 - Critique | AI112: Aucun plan d'action à ce niveau, étant donné la spécificité de ce marché | AJ112: T1-2026 | AK112: Location plutôt qu'Achat | AL112: 0 | AM112: 0 | AN112: 0 | AO112: 0 | AP112: 0 | AQ112: 0 | AR112: Élément | AS112: sites/DNA948/Lists/Analyse de Portefeuille FINA | AT112: =IFERROR(ROUND(IF(Tableau_query__18[[#This Row],[Sous famille]]<>"",VLOOKUP(Tableau_query__18[[#This Row],[Sous famille]],'A013 TCD'!G:H,2,FALSE),VLOOKUP(Tableau_query__18[[#This Row],[Famille d''achat]],'A013 TCD'!D:E,2,FALSE))/1000,0),"") -> 223
A113: 120 | B113: Travaux - Structures et clos couvert | C113: 45797 | D113: Structures et clos couvert | E113: Travaux | F113: Lauriane MALARD | H113: 3 les spécifications obligent à des renégociations avec les fournisseurs, | I113: 1 de nombreux fournisseurs possèdent le parc requis, | J113: 0 sans impact pour l’achat, | K113: 1 la forte concurrence amène les fournisseurs à s’adapter, | L113: 0 aucune difficulté pour recourir à des produits de substitution, | M113: 3 les prévisions sont aléatoires, ce qui est préjudiciable aux négociations, | N113: 0 l’acheteur a toute latitude dans le choix du fournisseur, | O113: 0 il n’y a pas de limite géographique à l’achat, | P113: 2 les lourdeurs administratives occasionnent des retards de paiement des fournisseurs, | Q113: 5 le défaut de communication interne est à l’origine d’achats réalisés dans des conditions défavorables. | R113: 1 - Faible | S113: 0 - Nul | T113: 1 - Faible | U113: 1 - Faible | V113: 1 - Faible | W113: 0 - Nul | X113: 1 - Faible | Y113: 1 - Faible | Z113: 1 - Faible | AA113: 2 - Modéré | AB113: 0 - Nul | AC113: 3 - Important | AD113: 1 - Faible | AE113: 3 - Important | AF113: 3 - Important | AG113: 3 - Important | AH113: 1 - Très bon niveau | AI113: La famille "structures et clos couvert" représente 7 067 630,80€ HT commandé en 2024, soit 27% du montant total des commandes travaux. La notion de catalogue pour cette famille ne veut pas dire "contrat à bon de commande" mais qu'il y a eu une consultation (34 consultations avec 32 MAPA, 1 demande de devis et 1 PNSC). Ces contrats issus de consultation représentent 6 067 954,53€ H, nous sommes au-dessus du seuil d'un AOO. La mise en place d'un accord cadre à bon de commande est sans doute possible sur plusieurs familles mais il nous faut de la visibilité sur les volumes. | AJ113: T1 2026 | AL113: 8 | AM113: 3 | AN113: 4 | AO113: 8 | AP113: 4 | AQ113: 3.2 | AR113: Élément | AS113: sites/DNA948/Lists/Analyse de Portefeuille FINA | AT113: =IFERROR(ROUND(IF(Tableau_query__18[[#This Row],[Sous famille]]<>"",VLOOKUP(Tableau_query__18[[#This Row],[Sous famille]],'A013 TCD'!G:H,2,FALSE),VLOOKUP(Tableau_query__18[[#This Row],[Famille d''achat]],'A013 TCD'!D:E,2,FALSE))/1000,0),"") -> 5135
A114: 121 | B114: Travaux - Services de maîtrise d'oeuvre immobilière | C114: 45918 | D114: Services de maîtrise d'oeuvre immobilière | E114: Travaux | F114: Loic LECLERCQ | H114: 1 les modifications sont minimes et sans conséquence sur l’achat, | I114: 1 de nombreux fournisseurs possèdent le parc requis, | J114: 2 retarde l’achat en l’absence de responsabilité technique, | K114: 0 la qualité demandée correspond à la moyenne du marché, | L114: 0 aucune difficulté pour recourir à des produits de substitution, | M114: 5 les achats ne sont que des achats d’urgence par manque de prévisions. | N114: 0 l’acheteur a toute latitude dans le choix du fournisseur, | O114: 1 les limites géographiques imposées n’entraînent pas de frein à l’achat, | P114: 2 les lourdeurs administratives occasionnent des retards de paiement des fournisseurs, | Q114: 5 le défaut de communication interne est à l’origine d’achats réalisés dans des conditions défavorables. | R114: 1 - Faible | S114: 0 - Nul | T114: 1 - Faible | U114: 0 - Nul | V114: 2 - Modéré | W114: 1 - Faible | X114: 1 - Faible | Y114: 1 - Faible | Z114: 0 - Nul | AA114: 1 - Faible | AC114: 1 - Faible | AD114: 1 - Faible | AE114: 1 - Faible | AF114: 3 - Important | AG114: 1 - Faible | AH114: 1 - Très bon niveau | AI114: Poursuivre la mise en place d'accords cadres à bons de commande sur les MOE et prestations associées (géomètre, étude de sol, détection de réseaux, ...) en complément de ceux déjà existants (MOE, Diag, CTC et SPS). | AJ114: T4-2025 | AK114: Optimisation du cahier des charges techniques (amélioration des spécifications, cahier des charges fonctionnel) | AL114: 0 | AM114: 0 | AN114: 3.2 | AO114: 10.4 | AP114: 2.4 | AQ114: 3.2 | AR114: Élément | AS114: sites/DNA948/Lists/Analyse de Portefeuille FINA | AT114: =IFERROR(ROUND(IF(Tableau_query__18[[#This Row],[Sous famille]]<>"",VLOOKUP(Tableau_query__18[[#This Row],[Sous famille]],'A013 TCD'!G:H,2,FALSE),VLOOKUP(Tableau_query__18[[#This Row],[Famille d''achat]],'A013 TCD'!D:E,2,FALSE))/1000,0),"") -> 2236
A115: 122 | B115: Travaux - Revêtement de façade | C115: 46112 | D115: Revêtement de façade | E115: Travaux | F115: Paola ANTONELLI | G115: Travaux de peinture, isolation, revêtement de façades | H115: 0 elles rejoignent nos propres spécifications, | I115: 0 égale à la moyenne du secteur, | J115: 0 sans impact pour l’achat, | K115: 0 la qualité demandée correspond à la moyenne du marché, | L115: 0 aucune difficulté pour recourir à des produits de substitution, | M115: 0 les prévisions à moyen et long terme sont fiables, | N115: 1 les impositions correspondent au meilleur choix, | O115: 1 les limites géographiques imposées n’entraînent pas de frein à l’achat, | P115: 0 pas de lourdeur administrative, | Q115: 1 la communication est suffisante pour les besoins des achats, | R115: 1 - Faible | S115: 1 - Faible | T115: 2 - Modéré | U115: 1 - Faible | V115: 1 - Faible | W115: 1 - Faible | X115: 2 - Modéré | Y115: 1 - Faible | Z115: 2 - Modéré | AA115: 1 - Faible | AB115: 1 - Faible | AC115: 2 - Modéré | AD115: 2 - Modéré | AE115: 2 - Modéré | AF115: 1 - Faible | AG115: 2 - Modéré | AH115: 4 - Faible | AI115: Massification des consultations à prévoir pour les Travaux de peinture, isolation, revêtement de façades. Contrat cadre existant pour la maintenance et la réparation. | AJ115: T1-2026 | AK115: Optimisation de la mise en concurrence (choix procédure, allotissement, critères, pondération) | AL115: 0 | AM115: 3.5 | AO115: 0 | AP115: 0 | AQ115: 0 | AR115: Élément | AS115: sites/DNA948/Lists/Analyse de Portefeuille FINA | AT115: =IFERROR(ROUND(IF(Tableau_query__18[[#This Row],[Sous famille]]<>"",VLOOKUP(Tableau_query__18[[#This Row],[Sous famille]],'A013 TCD'!G:H,2,FALSE),VLOOKUP(Tableau_query__18[[#This Row],[Famille d''achat]],'A013 TCD'!D:E,2,FALSE))/1000,0),"") -> 438
A116: 123 | B116: Travaux - Installations techniques | C116: 45916 | D116: Installations techniques | E116: Travaux | F116: Lauriane MALARD | H116: 0 elles rejoignent nos propres spécifications, | I116: 0 égale à la moyenne du secteur, | J116: 1 les précisions nécessaires au fournisseur peuvent être obtenues sans difficulté, | K116: 1 la forte concurrence amène les fournisseurs à s’adapter, | L116: 0 aucune difficulté pour recourir à des produits de substitution, | M116: 3 les prévisions sont aléatoires, ce qui est préjudiciable aux négociations, | N116: 0 l’acheteur a toute latitude dans le choix du fournisseur, | O116: 0 il n’y a pas de limite géographique à l’achat, | P116: 2 les lourdeurs administratives occasionnent des retards de paiement des fournisseurs, | Q116: 5 le défaut de communication interne est à l’origine d’achats réalisés dans des conditions défavorables. | R116: 0 - Nul | S116: 0 - Nul | T116: 1 - Faible | U116: 0 - Nul | V116: 1 - Faible | W116: 0 - Nul | X116: 1 - Faible | Y116: 1 - Faible | Z116: 1 - Faible | AA116: 1 - Faible | AB116: 1 - Faible | AC116: 1 - Faible | AD116: 1 - Faible | AE116: 2 - Modéré | AF116: 3 - Important | AG116: 1 - Faible | AH116: 1 - Très bon niveau | AI116: Mise en place de contrat à bons de commande pour l'entretien/maintenance | AJ116: T1-2026 | AK116: Globalisation, mutualisation | AL116: 3.5 | AM116: 4 | AN116: 4.8 | AO116: 8 | AP116: 6.4 | AQ116: 3.2 | AR116: Élément | AS116: sites/DNA948/Lists/Analyse de Portefeuille FINA | AT116: =IFERROR(ROUND(IF(Tableau_query__18[[#This Row],[Sous famille]]<>"",VLOOKUP(Tableau_query__18[[#This Row],[Sous famille]],'A013 TCD'!G:H,2,FALSE),VLOOKUP(Tableau_query__18[[#This Row],[Famille d''achat]],'A013 TCD'!D:E,2,FALSE))/1000,0),"") -> 3050
A117: 124 | B117: Travaux - Infrastructures et VRD | C117: 45918 | D117: Infrastructures et VRD | E117: Travaux | F117: Loic LECLERCQ | H117: 1 les modifications sont minimes et sans conséquence sur l’achat, | I117: 1 de nombreux fournisseurs possèdent le parc requis, | J117: 1 les précisions nécessaires au fournisseur peuvent être obtenues sans difficulté, | K117: 0 la qualité demandée correspond à la moyenne du marché, | L117: 0 aucune difficulté pour recourir à des produits de substitution, | M117: 5 les achats ne sont que des achats d’urgence par manque de prévisions. | N117: 0 l’acheteur a toute latitude dans le choix du fournisseur, | O117: 2 les limites géographiques imposées limitent le choix de fournisseurs, | P117: 2 les lourdeurs administratives occasionnent des retards de paiement des fournisseurs, | Q117: 5 le défaut de communication interne est à l’origine d’achats réalisés dans des conditions défavorables. | R117: 0 - Nul | S117: 0 - Nul | T117: 1 - Faible | U117: 1 - Faible | V117: 2 - Modéré | W117: 0 - Nul | X117: 1 - Faible | Y117: 1 - Faible | Z117: 0 - Nul | AA117: 1 - Faible | AB117: 1 - Faible | AC117: 1 - Faible | AD117: 1 - Faible | AE117: 1 - Faible | AF117: 0 - Nul | AG117: 1 - Faible | AH117: 1 - Très bon niveau | AI117: Obtenir une planification sur l'année en cours et prévisions sur les années à venir pour mettre en place des contrats cadres. | AJ117: T4-2026 | AK117: Globalisation, mutualisation | AR117: Élément | AS117: sites/DNA948/Lists/Analyse de Portefeuille FINA | AT117: =IFERROR(ROUND(IF(Tableau_query__18[[#This Row],[Sous famille]]<>"",VLOOKUP(Tableau_query__18[[#This Row],[Sous famille]],'A013 TCD'!G:H,2,FALSE),VLOOKUP(Tableau_query__18[[#This Row],[Famille d''achat]],'A013 TCD'!D:E,2,FALSE))/1000,0),"") -> 3672
A118: 125 | B118: Travaux - Construction modulaire | C118: 46112 | D118: Construction modulaire | E118: Travaux | F118: Paola ANTONELLI | G118: Location de construction modulaire | H118: 4 les spécifications sont à l’origine d’une réduction du nombre de fournisseurs potentiel, | I118: 3 entraîne une réduction du nombre de fournisseurs potentiels, | J118: 0 sans impact pour l’achat, | K118: 3 entraîne une réduction du nombre de fournisseurs qualifiés, | M118: 1 les prévisions sont relativement satisfaisantes pour couvrir les besoins des acheteurs, | N118: 0 l’acheteur a toute latitude dans le choix du fournisseur, | O118: 0 il n’y a pas de limite géographique à l’achat, | P118: 0 pas de lourdeur administrative, | Q118: 2 les contacts sont rares avec les services non directement concernés par l’acte d’achat, | R118: 0 - Nul | S118: 0 - Nul | T118: 0 - Nul | U118: 2 - Modéré | V118: 0 - Nul | W118: 0 - Nul | X118: 1 - Faible | Y118: 2 - Modéré | Z118: 2 - Modéré | AA118: 2 - Modéré | AB118: 2 - Modéré | AC118: 2 - Modéré | AD118: 1 - Faible | AE118: 1 - Faible | AF118: 0 - Nul | AG118: 3 - Important | AH118: 5 - Critique | AI118: Les commandes à ce jour portent uniquement sur la sous-famille "Location de construction modulaire".; d'où l'analyse de ce sous-portefeuille. La nécessité sera d'organiser un contrat cadre à bons de commande et alloti géographiquement. | AJ118: TRIMESTRE 1-2026 | AK118: Location plutôt qu'Achat | AR118: Élément | AS118: sites/DNA948/Lists/Analyse de Portefeuille FINA | AT118: =IFERROR(ROUND(IF(Tableau_query__18[[#This Row],[Sous famille]]<>"",VLOOKUP(Tableau_query__18[[#This Row],[Sous famille]],'A013 TCD'!G:H,2,FALSE),VLOOKUP(Tableau_query__18[[#This Row],[Famille d''achat]],'A013 TCD'!D:E,2,FALSE))/1000,0),"") -> 9
A119: 126 | B119: Travaux - Aménagements intérieurs | C119: 45916 | D119: Aménagements intérieurs | E119: Travaux | F119: Lauriane MALARD | H119: 0 elles rejoignent nos propres spécifications, | I119: 1 de nombreux fournisseurs possèdent le parc requis, | J119: 1 les précisions nécessaires au fournisseur peuvent être obtenues sans difficulté, | K119: 0 la qualité demandée correspond à la moyenne du marché, | L119: 0 aucune difficulté pour recourir à des produits de substitution, | M119: 1 les prévisions sont relativement satisfaisantes pour couvrir les besoins des acheteurs, | N119: 0 l’acheteur a toute latitude dans le choix du fournisseur, | O119: 0 il n’y a pas de limite géographique à l’achat, | P119: 2 les lourdeurs administratives occasionnent des retards de paiement des fournisseurs, | Q119: 5 le défaut de communication interne est à l’origine d’achats réalisés dans des conditions défavorables. | R119: 0 - Nul | S119: 0 - Nul | T119: 2 - Modéré | U119: 1 - Faible | V119: 1 - Faible | W119: 0 - Nul | X119: 1 - Faible | Y119: 2 - Modéré | Z119: 1 - Faible | AA119: 1 - Faible | AB119: 0 - Nul | AC119: 1 - Faible | AD119: 2 - Modéré | AE119: 2 - Modéré | AF119: 3 - Important | AG119: 1 - Faible | AH119: 1 - Très bon niveau | AI119: Disposer d’une meilleure visibilité sur les dossiers à venir facilitera la mutualisation des besoins et contribuera à réduire le nombre de consultations. Regrouper les travaux d’installation de cloisons et de peinture pour éviter des interventions fractionnées et optimiser les coûts. | AK119: Globalisation, mutualisation | AL119: 3.5 | AM119: 7.5 | AN119: 4 | AO119: 9.6 | AP119: 4 | AQ119: 4 | AR119: Élément | AS119: sites/DNA948/Lists/Analyse de Portefeuille FINA | AT119: =IFERROR(ROUND(IF(Tableau_query__18[[#This Row],[Sous famille]]<>"",VLOOKUP(Tableau_query__18[[#This Row],[Sous famille]],'A013 TCD'!G:H,2,FALSE),VLOOKUP(Tableau_query__18[[#This Row],[Famille d''achat]],'A013 TCD'!D:E,2,FALSE))/1000,0),"") -> 2432
A120: 133 | B120: Prestations - Location et entretien linge | C120: 45939 | D120: Service de gestion de blanchisserie et de nettoyage à sec | E120: Prestations | F120: Anne-Sophie CANHAN | G120: Location entretien de linges | H120: 0 elles rejoignent nos propres spécifications, | I120: 0 égale à la moyenne du secteur, | J120: 4 occasionne des achats approximatifs, | K120: 0 la qualité demandée correspond à la moyenne du marché, | L120: 0 aucune difficulté pour recourir à des produits de substitution, | M120: 2 les variations d’activité sont mal évaluées, ce qui oblige à des révisions de contrats, | N120: 0 l’acheteur a toute latitude dans le choix du fournisseur, | O120: 0 il n’y a pas de limite géographique à l’achat, | P120: 0 pas de lourdeur administrative, | Q120: 3 la communication ne permet pas d’anticiper les besoins, | T120: 0 - Nul | U120: 0 - Nul | V120: 1 - Faible | X120: 1 - Faible | Y120: 1 - Faible | Z120: 1 - Faible | AC120: 1 - Faible | AD120: 1 - Faible | AE120: 1 - Faible | AG120: 1 - Faible | AH120: 1 - Très bon niveau | AI120: il y-a deux actions possible : externaliser en passant par le RESAH si cela peut se faire et si c'est financièrement et techniquement interessant, ou bien miser sur la conccurence. | AJ120: en cours | AK120: Faire ou faire faire (externalisation) | AL120: 2.5 | AM120: 1.5 | AN120: 3.2 | AO120: 4 | AP120: 1.6 | AQ120: 0 | AR120: Élément | AS120: sites/DNA948/Lists/Analyse de Portefeuille FINA | AT120: =IFERROR(ROUND(IF(Tableau_query__18[[#This Row],[Sous famille]]<>"",VLOOKUP(Tableau_query__18[[#This Row],[Sous famille]],'A013 TCD'!G:H,2,FALSE),VLOOKUP(Tableau_query__18[[#This Row],[Famille d''achat]],'A013 TCD'!D:E,2,FALSE))/1000,0),"") -> 108
A121: 134 | B121: Prestations - Location fontaine à eau | C121: 45966 | D121: Service d'hotellerie et de restauration | E121: Prestations | F121: Anne-Sophie CANHAN | G121: Location maintenance de fontaines à eau | H121: 1 les modifications sont minimes et sans conséquence sur l’achat, | I121: 1 de nombreux fournisseurs possèdent le parc requis, | J121: 1 les précisions nécessaires au fournisseur peuvent être obtenues sans difficulté, | L121: 0 aucune difficulté pour recourir à des produits de substitution, | M121: 0 les prévisions à moyen et long terme sont fiables, | N121: 0 l’acheteur a toute latitude dans le choix du fournisseur, | O121: 0 il n’y a pas de limite géographique à l’achat, | P121: 0 pas de lourdeur administrative, | Q121: 2 les contacts sont rares avec les services non directement concernés par l’acte d’achat, | T121: 0 - Nul | U121: 0 - Nul | V121: 0 - Nul | X121: 0 - Nul | Y121: 1 - Faible | Z121: 0 - Nul | AC121: 0 - Nul | AD121: 0 - Nul | AE121: 0 - Nul | AG121: 2 - Modéré | AH121: 0 - Sécurisé | AI121: challenger les prestataires en lice pour obtenir un meilleur prix | AJ121: en cours | AK121: Sourcing fournisseurs / benchmark (connaissance offre du marché, connaissance structures de coûts) | AL121: 1 | AM121: 0.5 | AN121: 2.4 | AO121: 1.6 | AP121: 1.6 | AQ121: 0 | AR121: Élément | AS121: sites/DNA948/Lists/Analyse de Portefeuille FINA | AT121: =IFERROR(ROUND(IF(Tableau_query__18[[#This Row],[Sous famille]]<>"",VLOOKUP(Tableau_query__18[[#This Row],[Sous famille]],'A013 TCD'!G:H,2,FALSE),VLOOKUP(Tableau_query__18[[#This Row],[Famille d''achat]],'A013 TCD'!D:E,2,FALSE))/1000,0),"") -> 128
A122: 135 | B122: Prestations - Assistance téléphonique | C122: 45975 | D122: Services de gardiennage et de surveillance | E122: Prestations | F122: Anne-sophie CANHAN | G122: Prestation d’assistance téléphonique Sécurité | AL122: 0 | AM122: 0 | AN122: 0 | AO122: 0 | AP122: 0 | AQ122: 0 | AR122: Élément | AS122: sites/DNA948/Lists/Analyse de Portefeuille FINA | AT122: =IFERROR(ROUND(IF(Tableau_query__18[[#This Row],[Sous famille]]<>"",VLOOKUP(Tableau_query__18[[#This Row],[Sous famille]],'A013 TCD'!G:H,2,FALSE),VLOOKUP(Tableau_query__18[[#This Row],[Famille d''achat]],'A013 TCD'!D:E,2,FALSE))/1000,0),"")
A123: 136 | B123: Prestations - Service 3D | C123: 45975 | D123: Service 3D - dératisation desinsectisation desinfection | E123: Prestations | F123: Anne-Sophie CANHAN | G123: Service 3D - dératisation desinsectisation desinfection | AL123: 0 | AM123: 0 | AN123: 0 | AO123: 0 | AP123: 0 | AQ123: 0 | AR123: Élément | AS123: sites/DNA948/Lists/Analyse de Portefeuille FINA | AT123: =IFERROR(ROUND(IF(Tableau_query__18[[#This Row],[Sous famille]]<>"",VLOOKUP(Tableau_query__18[[#This Row],[Sous famille]],'A013 TCD'!G:H,2,FALSE),VLOOKUP(Tableau_query__18[[#This Row],[Famille d''achat]],'A013 TCD'!D:E,2,FALSE))/1000,0),"") -> 360
A124: 137 | B124: Prestations - Alarme détection incendie | C124: 45975 | D124: Service de réparation et d'entretien de matériels de lutte contre l'incendie | E124: Prestations | F124: Anne-Sophie CANHAN | G124: Maintenance préventive et réparation de matériels de lutte contre l'incendie | AL124: 0 | AM124: 0 | AN124: 0 | AO124: 0 | AP124: 0 | AQ124: 0 | AR124: Élément | AS124: sites/DNA948/Lists/Analyse de Portefeuille FINA | AT124: =IFERROR(ROUND(IF(Tableau_query__18[[#This Row],[Sous famille]]<>"",VLOOKUP(Tableau_query__18[[#This Row],[Sous famille]],'A013 TCD'!G:H,2,FALSE),VLOOKUP(Tableau_query__18[[#This Row],[Famille d''achat]],'A013 TCD'!D:E,2,FALSE))/1000,0),"") -> 1134
A125: 138 | B125: Prestations - Protection et lutte contre les incendies | C125: 45975 | D125: Service de réparation et d'entretien de matériels de lutte contre l'incendie | E125: Prestations | F125: Anne-Sophie CANHAN | G125: Maintenance préventive et réparation de matériels de lutte contre l'incendie | AL125: 0 | AM125: 0 | AN125: 0 | AO125: 0 | AP125: 0 | AQ125: 0 | AR125: Élément | AS125: sites/DNA948/Lists/Analyse de Portefeuille FINA | AT125: =IFERROR(ROUND(IF(Tableau_query__18[[#This Row],[Sous famille]]<>"",VLOOKUP(Tableau_query__18[[#This Row],[Sous famille]],'A013 TCD'!G:H,2,FALSE),VLOOKUP(Tableau_query__18[[#This Row],[Famille d''achat]],'A013 TCD'!D:E,2,FALSE))/1000,0),"") -> 1134
A126: 139 | B126: Prestations - Services de certification pour la formation | C126: 45994 | D126: Services de certification pour la formation | E126: Prestations | F126: Ana-Maria REYES-RIPOLL | G126: Frais d'Inscriptions aux certifications | H126: 0 elles rejoignent nos propres spécifications, | I126: 1 de nombreux fournisseurs possèdent le parc requis, | J126: 1 les précisions nécessaires au fournisseur peuvent être obtenues sans difficulté, | L126: 3 oblige à n’acheter que des produits de substitution homologués, | N126: 3 quelques rares fournisseurs imposés peuvent faire l’objet d’une mise en concurrence, | O126: 0 il n’y a pas de limite géographique à l’achat, | P126: 0 pas de lourdeur administrative, | Q126: 1 la communication est suffisante pour les besoins des achats, | T126: 0 - Nul | U126: 0 - Nul | V126: 1 - Faible | X126: 0 - Nul | Y126: 2 - Modéré | Z126: 0 - Nul | AC126: 0 - Nul | AD126: 0 - Nul | AE126: 0 - Nul | AG126: 0 - Nul | AH126: 2 - Acceptable | AI126: La catégorie d’achat « Frais d’inscription aux certifications » couvre les certifications de la branche Aéronautique pour PDL et Occitanie, les certifications DALF/DELF pour le Territoire Digital, ainsi que, pour le siège, les frais liés aux audits et à la certification Apave Certification et à la certification CléA. Ces dépenses correspondent à des frais imposés par des organismes certificateurs désignés de manière exclusive (branche, réglementation, référentiels), ce qui ne permet pas de mise en concurrence ni la mise en place d’un marché formalisé pour ces frais unitaires, les tarifs étant généralement fixés par les organismes eux-mêmes. À côté de ces dépenses, le marché « Certification et qualification des soudeurs », attribué à Bureau Véritas Exploitation et en vigueur jusqu’au 27/03/2029, ne nécessite pas de renouvellement à court terme, mais implique un suivi des consommations et des besoins afin de préparer et ajuster le futur cahier des charges à l’échéance du marché. | AK126: Optimisation de la mise en concurrence (choix procédure, allotissement, critères, pondération) | AL126: 0 | AM126: 0 | AN126: 0 | AO126: 0 | AP126: 0 | AQ126: 0 | AR126: Élément | AS126: sites/DNA948/Lists/Analyse de Portefeuille FINA | AT126: =IFERROR(ROUND(IF(Tableau_query__18[[#This Row],[Sous famille]]<>"",VLOOKUP(Tableau_query__18[[#This Row],[Sous famille]],'A013 TCD'!G:H,2,FALSE),VLOOKUP(Tableau_query__18[[#This Row],[Famille d''achat]],'A013 TCD'!D:E,2,FALSE))/1000,0),"") -> 311
...

Sheet A013 TCD
A1: Segment | D1: Famille | G1: Sous-famille
A3: Étiquettes de lignes | B3: Somme de Montant commandé HT | D3: Étiquettes de lignes | E3: Somme de Montant commandé HT | G3: Étiquettes de lignes | H3: Somme de Montant commandé HT
A4: Informatique & Telecom | B4: 29013541 | D4: Aménagements intérieurs | E4: 2432389 | G4: Abonnement aux services de transport en commun | H4: 14769.96
A5: Matériels | B5: 23159711 | D5: Annonces et insertions | E5: 1080907.8 | G5: Abonnements revues supports dématérialisés | H5: 179917.8
A6: Prestations | B6: 1.3594749e+08 | D6: Audits et certifications | E6: 281863.85 | G6: Abonnements revues supports papier ou mixte | H6: 487500.24
A7: Travaux | B7: 40798700 | D7: Banchage | E7: 10505.261 | G7: Abrasifs | H7: 60576.764
A8: Total général | B8: 2.2891944e+08 | D8: Carburant non routier | E8: 93748.593 | G8: Absorbants et dépolluants | H8: 9198.16
D9: Carreleur | E9: 338311.9 | G9: Accès à distance et droit utilisation e-learning | H9: 102164.75
D10: Centre d'appel | E10: 1849742.1 | G10: Accessoires Carrosserie | H10: 122366.98
D11: Conseil et audit | E11: 4524370.6 | G11: Accessoires Chauffage et refroidissement | H11: 24940.38
D12: Construction modulaire | E12: 9376.12 | G12: Accessoires Couvreur zingueur | H12: 25033.956
D13: Contrôle reglementaire | E13: 1091829.4 | G13: Accessoires Cycle | H13: 8516.37
D14: Contrôle technique | E14: 16158.314 | G14: Accessoires de cloture | H14: 1600.62
D15: Courrier et affranchissements | E15: 2307644.1 | G15: Accessoires de finition | H15: 47422.068
D16: Couvreur-Zingueur | E16: 170374.17 | G16: Accessoires de finition pour les revêtements muraux | H16: 428.16
D17: Datacenter et Cloud | E17: 3581502 | G17: Accessoires de loisirs | H17: 22575.26
D18: Droits d'auteurs et prestations diverses | E18: 84671.48 | G18: Accessoires Echappement | H18: 413.41
D19: E-learning | E19: 117111.49 | G19: Accessoires Electricité | H19: 109218.43
D20: Electroportatifs | E20: 370096.52 | G20: Accessoires électriques | H20: 764182.3
... D122: Total général | E122: 2.2891944e+08 | G122: Contrôle des ambiances de travail, aération, ventilation | H122: 240772.54
G123: Contrôle des appareils de levage et manutention | H123: 120879.25
G124: Contrôle des ascenseurs et monte-charges | H124: 6323.7235
G125: Contrôle des dispositifs de protection incendie | H125: 26400.35
G126: Contrôle des équipements de protection | H126: 18192.579
G127: Contrôle des installations à énergie thermique | H127: 110845.07
G128: Contrôle des Installations Classées pour la Protection de l'Environnement (ICPE) | H128: 75398.81
G129: Contrôle des installations électriques et éclairage | H129: 230011.8
G130: Contrôle des installations sous pression | H130: 29838.21
G131: Contrôle des matèriels, engins et installations utilisés sur chantiers du BTP | H131: 4817
G132: Contrôle des portes et portails | H132: 19058.37
G133: Contrôle environnemental | H133: 7194.11
G134: Contrôle technique automobile | H134: 16158.314
... G554: Total général | H554: 2.2891944e+08
